{
  "items" : [ {
    "id" : 1189325,
    "url" : "aHR0cHM6Ly9zbW90cmV0YW5pbWUucnUvdHJhbnNsYXRpb25zL2VtYmVkLzcxMTIwOA==",
    "episode" : 1,
    "kind" : "оригинал",
    "language" : "original",
    "author" : ""
  }, {
    "id" : 1925020,
    "url" : "aHR0cDovL3lvdXR1YmUuY29tL2VtYmVkL0FiQW5aRjdCQWVz",
    "episode" : 1,
    "kind" : "оригинал",
    "language" : "original",
    "author" : ""
  }, {
    "id" : 1925023,
    "url" : "aHR0cDovL3lvdXR1YmUuY29tL2VtYmVkL2JKcnRmM05NN00w",
    "episode" : 1,
    "kind" : "оригинал",
    "language" : "original",
    "author" : "MS0y"
  }, {
    "id" : 1144999,
    "url" : "aHR0cHM6Ly9zbW90cmV0YW5pbWUucnUvdHJhbnNsYXRpb25zL2VtYmVkLzY0NzUxOA==",
    "episode" : 1,
    "kind" : "субтитры",
    "language" : "russian",
    "author" : ""
  }, {
    "id" : 1568768,
    "url" : "aHR0cDovL3ZpZGVvLnNpYm5ldC5ydS9zaGVsbC5waHA_dmlkZW9pZD0xNjQ1MjA3",
    "episode" : 1,
    "kind" : "субтитры",
    "language" : "russian",
    "author" : ""
  }, {
    "id" : 1925019,
    "url" : "aHR0cDovL3lvdXR1YmUuY29tL2VtYmVkL0Z2aTBVZU1GMDg0",
    "episode" : 2,
    "kind" : "оригинал",
    "language" : "original",
    "author" : ""
  } ]
}