{
  "items" : [ {
    "id" : 1243298,
    "url" : "aHR0cDovL3lvdXR1YmUuY29tL2VtYmVkLzFVQjJsLVRoQUpR",
    "episode" : 1,
    "kind" : "оригинал",
    "language" : "original",
    "author" : ""
  }, {
    "id" : 1243300,
    "url" : "aHR0cDovL3lvdXR1YmUuY29tL2VtYmVkL18wY1NteTdfUFpz",
    "episode" : 2,
    "kind" : "оригинал",
    "language" : "original",
    "author" : ""
  }, {
    "id" : 1243301,
    "url" : "aHR0cDovL3lvdXR1YmUuY29tL2VtYmVkL2xQMy12TmZsaHZZ",
    "episode" : 3,
    "kind" : "оригинал",
    "language" : "original",
    "author" : ""
  }, {
    "id" : 1243303,
    "url" : "aHR0cDovL3lvdXR1YmUuY29tL2VtYmVkL2FVOUt1N1pIWV9N",
    "episode" : 4,
    "kind" : "оригинал",
    "language" : "original",
    "author" : ""
  }, {
    "id" : 1243304,
    "url" : "aHR0cDovL3lvdXR1YmUuY29tL2VtYmVkL2hRWHBPUHpWSFY0",
    "episode" : 5,
    "kind" : "оригинал",
    "language" : "original",
    "author" : ""
  }, {
    "id" : 1243306,
    "url" : "aHR0cDovL3lvdXR1YmUuY29tL2VtYmVkL25rcFl5NDd1b1VN",
    "episode" : 6,
    "kind" : "оригинал",
    "language" : "original",
    "author" : ""
  }, {
    "id" : 1243310,
    "url" : "aHR0cDovL3lvdXR1YmUuY29tL2VtYmVkL3ZCZHB6WVd3T3hJ",
    "episode" : 7,
    "kind" : "оригинал",
    "language" : "original",
    "author" : ""
  }, {
    "id" : 1243312,
    "url" : "aHR0cDovL3lvdXR1YmUuY29tL2VtYmVkL3J2TEZ3Zk9uQTVR",
    "episode" : 8,
    "kind" : "оригинал",
    "language" : "original",
    "author" : ""
  }, {
    "id" : 1243314,
    "url" : "aHR0cDovL3lvdXR1YmUuY29tL2VtYmVkL0FwQ1FjWUpEY05F",
    "episode" : 9,
    "kind" : "оригинал",
    "language" : "original",
    "author" : ""
  }, {
    "id" : 1243316,
    "url" : "aHR0cDovL3lvdXR1YmUuY29tL2VtYmVkLzQtVUNEcXFTMkk0",
    "episode" : 10,
    "kind" : "оригинал",
    "language" : "original",
    "author" : ""
  }, {
    "id" : 1243328,
    "url" : "aHR0cDovL3lvdXR1YmUuY29tL2VtYmVkL0NQREczVjcyWjcw",
    "episode" : 11,
    "kind" : "оригинал",
    "language" : "original",
    "author" : ""
  }, {
    "id" : 1243353,
    "url" : "aHR0cDovL3lvdXR1YmUuY29tL2VtYmVkLzExaHoxRjgyYW9F",
    "episode" : 12,
    "kind" : "оригинал",
    "language" : "original",
    "author" : ""
  }, {
    "id" : 1243370,
    "url" : "aHR0cDovL3lvdXR1YmUuY29tL2VtYmVkL3RQNzNOb0Zhdmg0",
    "episode" : 13,
    "kind" : "оригинал",
    "language" : "original",
    "author" : ""
  }, {
    "id" : 1243371,
    "url" : "aHR0cDovL3lvdXR1YmUuY29tL2VtYmVkL0NFTWlTXzZCd3gw",
    "episode" : 14,
    "kind" : "оригинал",
    "language" : "original",
    "author" : ""
  }, {
    "id" : 1243373,
    "url" : "aHR0cDovL3lvdXR1YmUuY29tL2VtYmVkL0lYSVZmWDVlN3Fr",
    "episode" : 15,
    "kind" : "оригинал",
    "language" : "original",
    "author" : ""
  }, {
    "id" : 1243374,
    "url" : "aHR0cDovL3lvdXR1YmUuY29tL2VtYmVkL1VGU2NTaERINUZj",
    "episode" : 16,
    "kind" : "оригинал",
    "language" : "original",
    "author" : ""
  }, {
    "id" : 1243375,
    "url" : "aHR0cDovL3lvdXR1YmUuY29tL2VtYmVkLzh6SWxaXzRldFl3",
    "episode" : 17,
    "kind" : "оригинал",
    "language" : "original",
    "author" : ""
  }, {
    "id" : 1243376,
    "url" : "aHR0cDovL3lvdXR1YmUuY29tL2VtYmVkL2ozY1F1Vy1UM01z",
    "episode" : 18,
    "kind" : "оригинал",
    "language" : "original",
    "author" : ""
  }, {
    "id" : 1243377,
    "url" : "aHR0cDovL3lvdXR1YmUuY29tL2VtYmVkLy1sTFVUQ3pIMzhZ",
    "episode" : 19,
    "kind" : "оригинал",
    "language" : "original",
    "author" : ""
  }, {
    "id" : 1243378,
    "url" : "aHR0cDovL3lvdXR1YmUuY29tL2VtYmVkL1JHV2tUcUJqanFr",
    "episode" : 20,
    "kind" : "оригинал",
    "language" : "original",
    "author" : ""
  }, {
    "id" : 1243380,
    "url" : "aHR0cDovL3lvdXR1YmUuY29tL2VtYmVkL3dOdTByVmtlanVV",
    "episode" : 21,
    "kind" : "оригинал",
    "language" : "original",
    "author" : ""
  }, {
    "id" : 1243381,
    "url" : "aHR0cDovL3lvdXR1YmUuY29tL2VtYmVkL2hRMVdkeU9uQlJr",
    "episode" : 22,
    "kind" : "оригинал",
    "language" : "original",
    "author" : ""
  }, {
    "id" : 1243383,
    "url" : "aHR0cDovL3lvdXR1YmUuY29tL2VtYmVkL2VWZXZkNkRjSDFB",
    "episode" : 23,
    "kind" : "оригинал",
    "language" : "original",
    "author" : ""
  }, {
    "id" : 1243384,
    "url" : "aHR0cDovL3lvdXR1YmUuY29tL2VtYmVkL0pKa0h0RVFhV2JJ",
    "episode" : 24,
    "kind" : "оригинал",
    "language" : "original",
    "author" : ""
  } ]
}