{
  "items" : [ {
    "id" : 1781210,
    "url" : "aHR0cDovL3lvdXR1YmUuY29tL2VtYmVkL05CNmhDbXk2UmNj",
    "episode" : 1,
    "kind" : "субтитры",
    "language" : "english",
    "author" : "SHVidWtp"
  }, {
    "id" : 1781212,
    "url" : "aHR0cDovL3lvdXR1YmUuY29tL2VtYmVkL01VRXhtOUdVb0Fr",
    "episode" : 2,
    "kind" : "субтитры",
    "language" : "english",
    "author" : "SHVidWtp"
  }, {
    "id" : 1781213,
    "url" : "aHR0cDovL3lvdXR1YmUuY29tL2VtYmVkLzl1SERpMmFEbjdB",
    "episode" : 3,
    "kind" : "субтитры",
    "language" : "english",
    "author" : "SHVidWtp"
  }, {
    "id" : 1781214,
    "url" : "aHR0cDovL3lvdXR1YmUuY29tL2VtYmVkL2I1T3RwMlR5dnhJ",
    "episode" : 4,
    "kind" : "субтитры",
    "language" : "english",
    "author" : "SHVidWtp"
  }, {
    "id" : 1781217,
    "url" : "aHR0cDovL3lvdXR1YmUuY29tL2VtYmVkL3UwelFsdkhkdDZB",
    "episode" : 5,
    "kind" : "субтитры",
    "language" : "english",
    "author" : "SHVidWtp"
  }, {
    "id" : 1781218,
    "url" : "aHR0cDovL3lvdXR1YmUuY29tL2VtYmVkL1pyVzFmQUduVk5r",
    "episode" : 6,
    "kind" : "субтитры",
    "language" : "english",
    "author" : "SHVidWtp"
  }, {
    "id" : 1781222,
    "url" : "aHR0cDovL3lvdXR1YmUuY29tL2VtYmVkLzA5dDZaWWRwRnNz",
    "episode" : 7,
    "kind" : "субтитры",
    "language" : "english",
    "author" : "SHVidWtp"
  }, {
    "id" : 1781224,
    "url" : "aHR0cDovL3lvdXR1YmUuY29tL2VtYmVkL0l3aWl1NmtYNWxB",
    "episode" : 8,
    "kind" : "субтитры",
    "language" : "english",
    "author" : "SHVidWtp"
  }, {
    "id" : 1781225,
    "url" : "aHR0cDovL3lvdXR1YmUuY29tL2VtYmVkL3dlRGFOQ3pqWUR3",
    "episode" : 9,
    "kind" : "субтитры",
    "language" : "english",
    "author" : "SHVidWtp"
  }, {
    "id" : 1781226,
    "url" : "aHR0cDovL3lvdXR1YmUuY29tL2VtYmVkL2FnMnd2cnR1VEYw",
    "episode" : 10,
    "kind" : "субтитры",
    "language" : "english",
    "author" : "SHVidWtp"
  }, {
    "id" : 1781232,
    "url" : "aHR0cDovL3lvdXR1YmUuY29tL2VtYmVkLzZZbDVkLURBREtV",
    "episode" : 11,
    "kind" : "субтитры",
    "language" : "english",
    "author" : "SHVidWtp"
  }, {
    "id" : 1781235,
    "url" : "aHR0cDovL3lvdXR1YmUuY29tL2VtYmVkL01iODlmMHNySVN3",
    "episode" : 12,
    "kind" : "субтитры",
    "language" : "english",
    "author" : "SHVidWtp"
  } ]
}