{
  "items" : [ {
    "id" : 1447140,
    "url" : "aHR0cDovL3lvdXR1YmUuY29tL2VtYmVkL09yZEtYQTlQQVBz",
    "episode" : 1,
    "kind" : "оригинал",
    "language" : "original",
    "author" : ""
  }, {
    "id" : 1447210,
    "url" : "aHR0cDovL3ZrLmNvbS92aWRlb19leHQucGhwP29pZD0zNzM3NDcwODQmaWQ9NDU2MjM5MTc0Jmhhc2g9NjhiMDdmNGU2MmMyYjkwMg==",
    "episode" : 1,
    "kind" : "оригинал",
    "language" : "original",
    "author" : "MS03"
  }, {
    "id" : 1447153,
    "url" : "aHR0cDovL3lvdXR1YmUuY29tL2VtYmVkL3dFVEVPWUJEbGFv",
    "episode" : 2,
    "kind" : "оригинал",
    "language" : "original",
    "author" : ""
  }, {
    "id" : 1447156,
    "url" : "aHR0cDovL3lvdXR1YmUuY29tL2VtYmVkL0ZNZjc1ZTJrbElN",
    "episode" : 3,
    "kind" : "оригинал",
    "language" : "original",
    "author" : ""
  }, {
    "id" : 1447161,
    "url" : "aHR0cDovL3lvdXR1YmUuY29tL2VtYmVkL0Z6Zk1BYkdEMUQ0",
    "episode" : 4,
    "kind" : "оригинал",
    "language" : "original",
    "author" : ""
  }, {
    "id" : 1447173,
    "url" : "aHR0cDovL3lvdXR1YmUuY29tL2VtYmVkL1ZtaDIxQ1dIZ0RJ",
    "episode" : 5,
    "kind" : "оригинал",
    "language" : "original",
    "author" : ""
  }, {
    "id" : 1447178,
    "url" : "aHR0cDovL3lvdXR1YmUuY29tL2VtYmVkL09aNkhQX3J2UThB",
    "episode" : 6,
    "kind" : "оригинал",
    "language" : "original",
    "author" : ""
  }, {
    "id" : 1447184,
    "url" : "aHR0cDovL3lvdXR1YmUuY29tL2VtYmVkL0k0T2c4ZVRFemFR",
    "episode" : 7,
    "kind" : "оригинал",
    "language" : "original",
    "author" : ""
  } ]
}