{
  "items" : [ {
    "id" : 1547067,
    "url" : "aHR0cDovL3lvdXR1YmUuY29tL2VtYmVkL2kzV1ZRX0RzdENB",
    "episode" : 1,
    "kind" : "оригинал",
    "language" : "original",
    "author" : ""
  }, {
    "id" : 1547068,
    "url" : "aHR0cDovL3lvdXR1YmUuY29tL2VtYmVkLzJ6RWFPSVFhVEtZ",
    "episode" : 2,
    "kind" : "оригинал",
    "language" : "original",
    "author" : ""
  }, {
    "id" : 1547069,
    "url" : "aHR0cDovL3lvdXR1YmUuY29tL2VtYmVkL0EydDlqdWZteG9r",
    "episode" : 3,
    "kind" : "оригинал",
    "language" : "original",
    "author" : ""
  }, {
    "id" : 1547070,
    "url" : "aHR0cDovL3lvdXR1YmUuY29tL2VtYmVkL0dETFpncG5VTVQ4",
    "episode" : 4,
    "kind" : "оригинал",
    "language" : "original",
    "author" : ""
  }, {
    "id" : 1547071,
    "url" : "aHR0cDovL3lvdXR1YmUuY29tL2VtYmVkL3lLeFRCc1BQOE5j",
    "episode" : 5,
    "kind" : "оригинал",
    "language" : "original",
    "author" : ""
  }, {
    "id" : 1547072,
    "url" : "aHR0cDovL3lvdXR1YmUuY29tL2VtYmVkL29Ra1AwRzZGcXY4",
    "episode" : 6,
    "kind" : "оригинал",
    "language" : "original",
    "author" : ""
  }, {
    "id" : 1547073,
    "url" : "aHR0cDovL3lvdXR1YmUuY29tL2VtYmVkL2Y1SmswMnI2SkNj",
    "episode" : 7,
    "kind" : "оригинал",
    "language" : "original",
    "author" : ""
  }, {
    "id" : 1547074,
    "url" : "aHR0cDovL3lvdXR1YmUuY29tL2VtYmVkL2JnTENoOXFxVy1Z",
    "episode" : 8,
    "kind" : "оригинал",
    "language" : "original",
    "author" : ""
  }, {
    "id" : 1547075,
    "url" : "aHR0cDovL3lvdXR1YmUuY29tL2VtYmVkL2NfT3Z5T2ttWVh3",
    "episode" : 9,
    "kind" : "оригинал",
    "language" : "original",
    "author" : ""
  }, {
    "id" : 1547076,
    "url" : "aHR0cDovL3lvdXR1YmUuY29tL2VtYmVkL1hXay0wWjUwN3NB",
    "episode" : 10,
    "kind" : "оригинал",
    "language" : "original",
    "author" : ""
  }, {
    "id" : 1547077,
    "url" : "aHR0cDovL3lvdXR1YmUuY29tL2VtYmVkL2o3OE9pdjZHcy1V",
    "episode" : 11,
    "kind" : "оригинал",
    "language" : "original",
    "author" : ""
  }, {
    "id" : 1547078,
    "url" : "aHR0cDovL3lvdXR1YmUuY29tL2VtYmVkLzVlelZaZXltOWsw",
    "episode" : 12,
    "kind" : "оригинал",
    "language" : "original",
    "author" : ""
  }, {
    "id" : 1547079,
    "url" : "aHR0cDovL3lvdXR1YmUuY29tL2VtYmVkL3l1aF8zRGIxUHlF",
    "episode" : 13,
    "kind" : "оригинал",
    "language" : "original",
    "author" : ""
  }, {
    "id" : 1547080,
    "url" : "aHR0cDovL3lvdXR1YmUuY29tL2VtYmVkLzFXaWhNXzZuSnpj",
    "episode" : 14,
    "kind" : "оригинал",
    "language" : "original",
    "author" : ""
  }, {
    "id" : 1547081,
    "url" : "aHR0cDovL3lvdXR1YmUuY29tL2VtYmVkL2FiRXNXZ2xvR004",
    "episode" : 15,
    "kind" : "оригинал",
    "language" : "original",
    "author" : ""
  }, {
    "id" : 1547082,
    "url" : "aHR0cDovL3lvdXR1YmUuY29tL2VtYmVkL2o5THgxMTk4VWY0",
    "episode" : 16,
    "kind" : "оригинал",
    "language" : "original",
    "author" : ""
  }, {
    "id" : 1547083,
    "url" : "aHR0cDovL3lvdXR1YmUuY29tL2VtYmVkL1I3ckhTRDdwQTVV",
    "episode" : 17,
    "kind" : "оригинал",
    "language" : "original",
    "author" : ""
  }, {
    "id" : 1547084,
    "url" : "aHR0cDovL3lvdXR1YmUuY29tL2VtYmVkLy1hVkh6cDFSbXJB",
    "episode" : 18,
    "kind" : "оригинал",
    "language" : "original",
    "author" : ""
  }, {
    "id" : 1547085,
    "url" : "aHR0cDovL3lvdXR1YmUuY29tL2VtYmVkLzV0MzViY1lOd2Z3",
    "episode" : 19,
    "kind" : "оригинал",
    "language" : "original",
    "author" : ""
  }, {
    "id" : 1547086,
    "url" : "aHR0cDovL3lvdXR1YmUuY29tL2VtYmVkL2UyVGZuTnptcG84",
    "episode" : 20,
    "kind" : "оригинал",
    "language" : "original",
    "author" : ""
  }, {
    "id" : 1547087,
    "url" : "aHR0cDovL3lvdXR1YmUuY29tL2VtYmVkL1FRR1Z4WE53U3Q4",
    "episode" : 21,
    "kind" : "оригинал",
    "language" : "original",
    "author" : ""
  }, {
    "id" : 1547088,
    "url" : "aHR0cDovL3lvdXR1YmUuY29tL2VtYmVkL3NlcW5sOEJRS3JV",
    "episode" : 22,
    "kind" : "оригинал",
    "language" : "original",
    "author" : ""
  }, {
    "id" : 1547089,
    "url" : "aHR0cDovL3lvdXR1YmUuY29tL2VtYmVkL2J1RGVvRVNYTUdZ",
    "episode" : 23,
    "kind" : "оригинал",
    "language" : "original",
    "author" : ""
  }, {
    "id" : 1547090,
    "url" : "aHR0cDovL3lvdXR1YmUuY29tL2VtYmVkL3dSNlJpTTdaaFRv",
    "episode" : 24,
    "kind" : "оригинал",
    "language" : "original",
    "author" : ""
  }, {
    "id" : 1547091,
    "url" : "aHR0cDovL3lvdXR1YmUuY29tL2VtYmVkL2ZXcmlGQVZGVEZV",
    "episode" : 25,
    "kind" : "оригинал",
    "language" : "original",
    "author" : ""
  }, {
    "id" : 1547092,
    "url" : "aHR0cDovL3lvdXR1YmUuY29tL2VtYmVkLzRyQ3VzNGc0aDRz",
    "episode" : 26,
    "kind" : "оригинал",
    "language" : "original",
    "author" : ""
  }, {
    "id" : 1547094,
    "url" : "aHR0cDovL3lvdXR1YmUuY29tL2VtYmVkL0hnR3ViMUdzTkhJ",
    "episode" : 27,
    "kind" : "оригинал",
    "language" : "original",
    "author" : ""
  }, {
    "id" : 1547095,
    "url" : "aHR0cDovL3lvdXR1YmUuY29tL2VtYmVkLzdFcHRBWjlOcktB",
    "episode" : 28,
    "kind" : "оригинал",
    "language" : "original",
    "author" : ""
  }, {
    "id" : 1547096,
    "url" : "aHR0cDovL3lvdXR1YmUuY29tL2VtYmVkL202d24zaGIxYy1v",
    "episode" : 29,
    "kind" : "оригинал",
    "language" : "original",
    "author" : ""
  }, {
    "id" : 1547097,
    "url" : "aHR0cDovL3lvdXR1YmUuY29tL2VtYmVkL2dtckxQSi1CZHR3",
    "episode" : 30,
    "kind" : "оригинал",
    "language" : "original",
    "author" : ""
  }, {
    "id" : 1547098,
    "url" : "aHR0cDovL3lvdXR1YmUuY29tL2VtYmVkLzJzSEhrVXhERHJF",
    "episode" : 31,
    "kind" : "оригинал",
    "language" : "original",
    "author" : ""
  }, {
    "id" : 1547099,
    "url" : "aHR0cDovL3lvdXR1YmUuY29tL2VtYmVkL2hNMURYOVhDM3Fn",
    "episode" : 32,
    "kind" : "оригинал",
    "language" : "original",
    "author" : ""
  }, {
    "id" : 1547100,
    "url" : "aHR0cDovL3lvdXR1YmUuY29tL2VtYmVkL1g4Q2Y0bTRQbThJ",
    "episode" : 33,
    "kind" : "оригинал",
    "language" : "original",
    "author" : ""
  }, {
    "id" : 1547101,
    "url" : "aHR0cDovL3lvdXR1YmUuY29tL2VtYmVkL2RQYWJiRTlzWU9R",
    "episode" : 34,
    "kind" : "оригинал",
    "language" : "original",
    "author" : ""
  }, {
    "id" : 1547102,
    "url" : "aHR0cDovL3lvdXR1YmUuY29tL2VtYmVkL3RVR05FNENRbmlJ",
    "episode" : 35,
    "kind" : "оригинал",
    "language" : "original",
    "author" : ""
  }, {
    "id" : 1547103,
    "url" : "aHR0cDovL3lvdXR1YmUuY29tL2VtYmVkL3lPaXNwaEZTR05V",
    "episode" : 36,
    "kind" : "оригинал",
    "language" : "original",
    "author" : ""
  }, {
    "id" : 1547104,
    "url" : "aHR0cDovL3lvdXR1YmUuY29tL2VtYmVkL1RIS0RNd2I5T2w0",
    "episode" : 37,
    "kind" : "оригинал",
    "language" : "original",
    "author" : ""
  }, {
    "id" : 1547105,
    "url" : "aHR0cDovL3lvdXR1YmUuY29tL2VtYmVkLy1Ob3hiZ3g3WDhv",
    "episode" : 38,
    "kind" : "оригинал",
    "language" : "original",
    "author" : ""
  }, {
    "id" : 1547106,
    "url" : "aHR0cDovL3lvdXR1YmUuY29tL2VtYmVkLzBpSHg2NzNnZzVF",
    "episode" : 39,
    "kind" : "оригинал",
    "language" : "original",
    "author" : ""
  }, {
    "id" : 1547107,
    "url" : "aHR0cDovL3lvdXR1YmUuY29tL2VtYmVkL1h4MzlqRVhuSTQw",
    "episode" : 40,
    "kind" : "оригинал",
    "language" : "original",
    "author" : ""
  }, {
    "id" : 1547108,
    "url" : "aHR0cDovL3lvdXR1YmUuY29tL2VtYmVkL1N1dWlpckJFUWtF",
    "episode" : 41,
    "kind" : "оригинал",
    "language" : "original",
    "author" : ""
  }, {
    "id" : 1547109,
    "url" : "aHR0cDovL3lvdXR1YmUuY29tL2VtYmVkL0RpMWVFSmVlak1J",
    "episode" : 42,
    "kind" : "оригинал",
    "language" : "original",
    "author" : ""
  }, {
    "id" : 1547110,
    "url" : "aHR0cDovL3lvdXR1YmUuY29tL2VtYmVkL0hnd3M4MV9Sd1cw",
    "episode" : 43,
    "kind" : "оригинал",
    "language" : "original",
    "author" : ""
  }, {
    "id" : 1547111,
    "url" : "aHR0cDovL3lvdXR1YmUuY29tL2VtYmVkL0pTdmp4UTBURWZR",
    "episode" : 44,
    "kind" : "оригинал",
    "language" : "original",
    "author" : ""
  }, {
    "id" : 1547112,
    "url" : "aHR0cDovL3lvdXR1YmUuY29tL2VtYmVkL2sycC04ZFJodWlR",
    "episode" : 45,
    "kind" : "оригинал",
    "language" : "original",
    "author" : ""
  }, {
    "id" : 1547113,
    "url" : "aHR0cDovL3lvdXR1YmUuY29tL2VtYmVkL2hWOEFiZFhHeURN",
    "episode" : 46,
    "kind" : "оригинал",
    "language" : "original",
    "author" : ""
  }, {
    "id" : 1547115,
    "url" : "aHR0cDovL3lvdXR1YmUuY29tL2VtYmVkLzZUeGlYWHdLLWFF",
    "episode" : 47,
    "kind" : "оригинал",
    "language" : "original",
    "author" : ""
  }, {
    "id" : 1547116,
    "url" : "aHR0cDovL3lvdXR1YmUuY29tL2VtYmVkL25kbGhVS2pDbUhR",
    "episode" : 48,
    "kind" : "оригинал",
    "language" : "original",
    "author" : ""
  }, {
    "id" : 1547117,
    "url" : "aHR0cDovL3lvdXR1YmUuY29tL2VtYmVkL1d6X3JYSEJ4Q09z",
    "episode" : 49,
    "kind" : "оригинал",
    "language" : "original",
    "author" : ""
  }, {
    "id" : 1547118,
    "url" : "aHR0cDovL3lvdXR1YmUuY29tL2VtYmVkL3BnbG9HbHlPTGlN",
    "episode" : 50,
    "kind" : "оригинал",
    "language" : "original",
    "author" : ""
  }, {
    "id" : 1547119,
    "url" : "aHR0cDovL3lvdXR1YmUuY29tL2VtYmVkL3NCY0RqZ00xWGhj",
    "episode" : 51,
    "kind" : "оригинал",
    "language" : "original",
    "author" : ""
  }, {
    "id" : 1547120,
    "url" : "aHR0cDovL3lvdXR1YmUuY29tL2VtYmVkLzlpM0NUNXNmQTlF",
    "episode" : 52,
    "kind" : "оригинал",
    "language" : "original",
    "author" : ""
  }, {
    "id" : 1547121,
    "url" : "aHR0cDovL3lvdXR1YmUuY29tL2VtYmVkL0NIRWVxaGhRVjFZ",
    "episode" : 53,
    "kind" : "оригинал",
    "language" : "original",
    "author" : ""
  }, {
    "id" : 1547122,
    "url" : "aHR0cDovL3lvdXR1YmUuY29tL2VtYmVkL19qVV9TOS1zLXFR",
    "episode" : 54,
    "kind" : "оригинал",
    "language" : "original",
    "author" : ""
  }, {
    "id" : 1547123,
    "url" : "aHR0cDovL3lvdXR1YmUuY29tL2VtYmVkL3h0NjBiZzJ4eVpV",
    "episode" : 55,
    "kind" : "оригинал",
    "language" : "original",
    "author" : ""
  }, {
    "id" : 1547124,
    "url" : "aHR0cDovL3lvdXR1YmUuY29tL2VtYmVkLzRtNTF3VS1XaWxZ",
    "episode" : 56,
    "kind" : "оригинал",
    "language" : "original",
    "author" : ""
  }, {
    "id" : 1547128,
    "url" : "aHR0cDovL3lvdXR1YmUuY29tL2VtYmVkL2FBWHRzVExQTkRn",
    "episode" : 57,
    "kind" : "оригинал",
    "language" : "original",
    "author" : ""
  }, {
    "id" : 1547129,
    "url" : "aHR0cDovL3lvdXR1YmUuY29tL2VtYmVkL3pwZEt6clFUSzcw",
    "episode" : 58,
    "kind" : "оригинал",
    "language" : "original",
    "author" : ""
  }, {
    "id" : 1547130,
    "url" : "aHR0cDovL3lvdXR1YmUuY29tL2VtYmVkL0VEdXNldE9BTkg4",
    "episode" : 59,
    "kind" : "оригинал",
    "language" : "original",
    "author" : ""
  }, {
    "id" : 1547131,
    "url" : "aHR0cDovL3lvdXR1YmUuY29tL2VtYmVkL1pKajRYaW5QT2U4",
    "episode" : 60,
    "kind" : "оригинал",
    "language" : "original",
    "author" : ""
  }, {
    "id" : 1547132,
    "url" : "aHR0cDovL3lvdXR1YmUuY29tL2VtYmVkL29FZkc4QXdEMDln",
    "episode" : 61,
    "kind" : "оригинал",
    "language" : "original",
    "author" : ""
  }, {
    "id" : 1547133,
    "url" : "aHR0cDovL3lvdXR1YmUuY29tL2VtYmVkL1JlMEZ6bjhPVlhV",
    "episode" : 62,
    "kind" : "оригинал",
    "language" : "original",
    "author" : ""
  }, {
    "id" : 1547134,
    "url" : "aHR0cDovL3lvdXR1YmUuY29tL2VtYmVkL1g3RFFFTDIwVXJV",
    "episode" : 63,
    "kind" : "оригинал",
    "language" : "original",
    "author" : ""
  }, {
    "id" : 1547135,
    "url" : "aHR0cDovL3lvdXR1YmUuY29tL2VtYmVkL3h5WElpNnhqQ3M4",
    "episode" : 64,
    "kind" : "оригинал",
    "language" : "original",
    "author" : ""
  }, {
    "id" : 1547136,
    "url" : "aHR0cDovL3lvdXR1YmUuY29tL2VtYmVkL3JRTmVNanNEdWZr",
    "episode" : 65,
    "kind" : "оригинал",
    "language" : "original",
    "author" : ""
  }, {
    "id" : 1547066,
    "url" : "aHR0cDovL3lvdXR1YmUuY29tL2VtYmVkL3BtQ1czQ3pxdzRr",
    "episode" : 66,
    "kind" : "оригинал",
    "language" : "original",
    "author" : ""
  }, {
    "id" : 1547138,
    "url" : "aHR0cDovL3lvdXR1YmUuY29tL2VtYmVkL0FVVHhWcjc4UUpn",
    "episode" : 67,
    "kind" : "оригинал",
    "language" : "original",
    "author" : ""
  }, {
    "id" : 1547139,
    "url" : "aHR0cDovL3lvdXR1YmUuY29tL2VtYmVkL2Z3ZEQ1X1E5d2h3",
    "episode" : 68,
    "kind" : "оригинал",
    "language" : "original",
    "author" : ""
  }, {
    "id" : 1547140,
    "url" : "aHR0cDovL3lvdXR1YmUuY29tL2VtYmVkL2RoRlZvcUlDdl9Z",
    "episode" : 69,
    "kind" : "оригинал",
    "language" : "original",
    "author" : ""
  }, {
    "id" : 1547141,
    "url" : "aHR0cDovL3lvdXR1YmUuY29tL2VtYmVkL0NOdzYtOUk2TnI0",
    "episode" : 70,
    "kind" : "оригинал",
    "language" : "original",
    "author" : ""
  }, {
    "id" : 1547142,
    "url" : "aHR0cDovL3lvdXR1YmUuY29tL2VtYmVkL2Rna284RlhxMFM4",
    "episode" : 71,
    "kind" : "оригинал",
    "language" : "original",
    "author" : ""
  }, {
    "id" : 1795463,
    "url" : "aHR0cDovL3lvdXR1YmUuY29tL2VtYmVkL0Y4ek1JQnJHMWdR",
    "episode" : 72,
    "kind" : "оригинал",
    "language" : "original",
    "author" : ""
  }, {
    "id" : 1795464,
    "url" : "aHR0cDovL3lvdXR1YmUuY29tL2VtYmVkL2lYQko4Qm5sbmpv",
    "episode" : 73,
    "kind" : "оригинал",
    "language" : "original",
    "author" : ""
  }, {
    "id" : 1795465,
    "url" : "aHR0cDovL3lvdXR1YmUuY29tL2VtYmVkL0t5YzVzd090ZWZn",
    "episode" : 74,
    "kind" : "оригинал",
    "language" : "original",
    "author" : ""
  }, {
    "id" : 1795466,
    "url" : "aHR0cDovL3lvdXR1YmUuY29tL2VtYmVkL2M1RXdHZUQ2azhz",
    "episode" : 75,
    "kind" : "оригинал",
    "language" : "original",
    "author" : ""
  }, {
    "id" : 1795467,
    "url" : "aHR0cDovL3lvdXR1YmUuY29tL2VtYmVkL0xweF9icW9NaHk4",
    "episode" : 76,
    "kind" : "оригинал",
    "language" : "original",
    "author" : ""
  }, {
    "id" : 1795468,
    "url" : "aHR0cDovL3lvdXR1YmUuY29tL2VtYmVkL2RzQlRnZ3JVVzJj",
    "episode" : 77,
    "kind" : "оригинал",
    "language" : "original",
    "author" : ""
  }, {
    "id" : 1795469,
    "url" : "aHR0cDovL3lvdXR1YmUuY29tL2VtYmVkL1REYlhmWUxXYXBZ",
    "episode" : 78,
    "kind" : "оригинал",
    "language" : "original",
    "author" : ""
  }, {
    "id" : 1795470,
    "url" : "aHR0cDovL3lvdXR1YmUuY29tL2VtYmVkL2JkNUR3aGp2bmQ4",
    "episode" : 79,
    "kind" : "оригинал",
    "language" : "original",
    "author" : ""
  }, {
    "id" : 1795471,
    "url" : "aHR0cDovL3lvdXR1YmUuY29tL2VtYmVkL0VHajI2b0NRbm1z",
    "episode" : 80,
    "kind" : "оригинал",
    "language" : "original",
    "author" : ""
  }, {
    "id" : 1795472,
    "url" : "aHR0cDovL3lvdXR1YmUuY29tL2VtYmVkL1N3RXpoNzZFQmJZ",
    "episode" : 81,
    "kind" : "оригинал",
    "language" : "original",
    "author" : ""
  }, {
    "id" : 1795473,
    "url" : "aHR0cDovL3lvdXR1YmUuY29tL2VtYmVkLzVMdDVjdjFmRmcw",
    "episode" : 82,
    "kind" : "оригинал",
    "language" : "original",
    "author" : ""
  }, {
    "id" : 1795474,
    "url" : "aHR0cDovL3lvdXR1YmUuY29tL2VtYmVkL01nRWpRZWpFTjM0",
    "episode" : 83,
    "kind" : "оригинал",
    "language" : "original",
    "author" : ""
  } ]
}