{
  "items" : [ {
    "id" : 1919744,
    "url" : "aHR0cDovL3lvdXR1YmUuY29tL2VtYmVkL29KYmxJSjZ0ZlI4",
    "episode" : 1,
    "kind" : "оригинал",
    "language" : "original",
    "author" : ""
  }, {
    "id" : 1297728,
    "url" : "aHR0cDovL3lvdXR1YmUuY29tL2VtYmVkL0NobEJ2VE9qZVJn",
    "episode" : 1,
    "kind" : "субтитры",
    "language" : "original",
    "author" : "0LDQvdCz0LvQuNC50YHQutC40LUg0YHRg9Cx0YLQuNGC0YDRiw=="
  }, {
    "id" : 1919745,
    "url" : "aHR0cDovL3lvdXR1YmUuY29tL2VtYmVkL2h2V0ZjSnpGRWhr",
    "episode" : 2,
    "kind" : "оригинал",
    "language" : "original",
    "author" : ""
  }, {
    "id" : 1919746,
    "url" : "aHR0cDovL3lvdXR1YmUuY29tL2VtYmVkL1BGbF9WRWN2S0ow",
    "episode" : 3,
    "kind" : "оригинал",
    "language" : "original",
    "author" : ""
  }, {
    "id" : 1919748,
    "url" : "aHR0cDovL3lvdXR1YmUuY29tL2VtYmVkL0pMOV9xQjh1ekQ4",
    "episode" : 4,
    "kind" : "оригинал",
    "language" : "original",
    "author" : ""
  }, {
    "id" : 1919749,
    "url" : "aHR0cDovL3lvdXR1YmUuY29tL2VtYmVkL1J0UDZqNndwMU5z",
    "episode" : 5,
    "kind" : "оригинал",
    "language" : "original",
    "author" : ""
  }, {
    "id" : 1919751,
    "url" : "aHR0cDovL3lvdXR1YmUuY29tL2VtYmVkL2NPQks0VTNWdng0",
    "episode" : 6,
    "kind" : "оригинал",
    "language" : "original",
    "author" : ""
  }, {
    "id" : 1919752,
    "url" : "aHR0cDovL3lvdXR1YmUuY29tL2VtYmVkL29wM2xBa255UWp3",
    "episode" : 7,
    "kind" : "оригинал",
    "language" : "original",
    "author" : ""
  }, {
    "id" : 1919754,
    "url" : "aHR0cDovL3lvdXR1YmUuY29tL2VtYmVkL1dpbmg4RkxZeUZZ",
    "episode" : 8,
    "kind" : "оригинал",
    "language" : "original",
    "author" : ""
  }, {
    "id" : 1919755,
    "url" : "aHR0cDovL3lvdXR1YmUuY29tL2VtYmVkL19DQkowRzVRRGZR",
    "episode" : 9,
    "kind" : "оригинал",
    "language" : "original",
    "author" : ""
  }, {
    "id" : 1919756,
    "url" : "aHR0cDovL3lvdXR1YmUuY29tL2VtYmVkL240OFdYUi10Zl9B",
    "episode" : 10,
    "kind" : "оригинал",
    "language" : "original",
    "author" : ""
  } ]
}