{
  "items" : [ {
    "id" : 1919279,
    "url" : "aHR0cDovL3lvdXR1YmUuY29tL2VtYmVkL1I2Vi1rZ093RTNJ",
    "episode" : 1,
    "kind" : "оригинал",
    "language" : "original",
    "author" : ""
  }, {
    "id" : 1919280,
    "url" : "aHR0cDovL3lvdXR1YmUuY29tL2VtYmVkL3ZZYmY4YVUwM09B",
    "episode" : 2,
    "kind" : "оригинал",
    "language" : "original",
    "author" : ""
  }, {
    "id" : 1919281,
    "url" : "aHR0cDovL3lvdXR1YmUuY29tL2VtYmVkL080NnhnTi1lUWdv",
    "episode" : 3,
    "kind" : "оригинал",
    "language" : "original",
    "author" : ""
  }, {
    "id" : 1919282,
    "url" : "aHR0cDovL3lvdXR1YmUuY29tL2VtYmVkL1NPYWJndHgtbV9Z",
    "episode" : 4,
    "kind" : "оригинал",
    "language" : "original",
    "author" : ""
  }, {
    "id" : 1919283,
    "url" : "aHR0cDovL3lvdXR1YmUuY29tL2VtYmVkL0RDOW83N1lmWFZj",
    "episode" : 5,
    "kind" : "оригинал",
    "language" : "original",
    "author" : ""
  }, {
    "id" : 1919284,
    "url" : "aHR0cDovL3lvdXR1YmUuY29tL2VtYmVkLzV1Yll2d3QzNnVz",
    "episode" : 6,
    "kind" : "оригинал",
    "language" : "original",
    "author" : ""
  }, {
    "id" : 1919285,
    "url" : "aHR0cDovL3lvdXR1YmUuY29tL2VtYmVkL01lMTVrOXRobGh3",
    "episode" : 7,
    "kind" : "оригинал",
    "language" : "original",
    "author" : ""
  }, {
    "id" : 1919286,
    "url" : "aHR0cDovL3lvdXR1YmUuY29tL2VtYmVkL201TTVLLThnRFRZ",
    "episode" : 8,
    "kind" : "оригинал",
    "language" : "original",
    "author" : ""
  }, {
    "id" : 1919287,
    "url" : "aHR0cDovL3lvdXR1YmUuY29tL2VtYmVkL2U0RUdZWDVmbnNR",
    "episode" : 9,
    "kind" : "оригинал",
    "language" : "original",
    "author" : ""
  }, {
    "id" : 1919288,
    "url" : "aHR0cDovL3lvdXR1YmUuY29tL2VtYmVkL3JBU0t5X1hOWHo4",
    "episode" : 10,
    "kind" : "оригинал",
    "language" : "original",
    "author" : ""
  }, {
    "id" : 1919289,
    "url" : "aHR0cDovL3lvdXR1YmUuY29tL2VtYmVkL20zcUF4VnhfREdr",
    "episode" : 11,
    "kind" : "оригинал",
    "language" : "original",
    "author" : ""
  } ]
}