{
  "items" : [ {
    "id" : 1897818,
    "url" : "aHR0cDovL3lvdXR1YmUuY29tL2VtYmVkL0ZLV2hjUFF6RHN3",
    "episode" : 1,
    "kind" : "оригинал",
    "language" : "original",
    "author" : ""
  }, {
    "id" : 1897819,
    "url" : "aHR0cDovL3lvdXR1YmUuY29tL2VtYmVkLzBCQ3BvQ2xGWVZB",
    "episode" : 2,
    "kind" : "оригинал",
    "language" : "original",
    "author" : ""
  }, {
    "id" : 1897820,
    "url" : "aHR0cDovL3lvdXR1YmUuY29tL2VtYmVkL2RBOUpTWnNsclZJ",
    "episode" : 3,
    "kind" : "оригинал",
    "language" : "original",
    "author" : ""
  }, {
    "id" : 1897821,
    "url" : "aHR0cDovL3lvdXR1YmUuY29tL2VtYmVkL2xPb21ENjh2eGhn",
    "episode" : 4,
    "kind" : "оригинал",
    "language" : "original",
    "author" : ""
  }, {
    "id" : 1897822,
    "url" : "aHR0cDovL3lvdXR1YmUuY29tL2VtYmVkL2pqendISkFFUi1n",
    "episode" : 5,
    "kind" : "оригинал",
    "language" : "original",
    "author" : ""
  }, {
    "id" : 1897823,
    "url" : "aHR0cDovL3lvdXR1YmUuY29tL2VtYmVkL2tOeHlTQWFGTGN3",
    "episode" : 6,
    "kind" : "оригинал",
    "language" : "original",
    "author" : ""
  }, {
    "id" : 1897824,
    "url" : "aHR0cDovL3lvdXR1YmUuY29tL2VtYmVkL2xmcnhHUDdUbnFZ",
    "episode" : 7,
    "kind" : "оригинал",
    "language" : "original",
    "author" : ""
  }, {
    "id" : 1897825,
    "url" : "aHR0cDovL3lvdXR1YmUuY29tL2VtYmVkLzN5YTV3bmhWOWd3",
    "episode" : 8,
    "kind" : "оригинал",
    "language" : "original",
    "author" : ""
  }, {
    "id" : 1897826,
    "url" : "aHR0cDovL3lvdXR1YmUuY29tL2VtYmVkL1hmR3Z2WG1DamE0",
    "episode" : 9,
    "kind" : "оригинал",
    "language" : "original",
    "author" : ""
  }, {
    "id" : 1897827,
    "url" : "aHR0cDovL3lvdXR1YmUuY29tL2VtYmVkL1NYTy1JVUFad0Fr",
    "episode" : 10,
    "kind" : "оригинал",
    "language" : "original",
    "author" : ""
  }, {
    "id" : 1897828,
    "url" : "aHR0cDovL3lvdXR1YmUuY29tL2VtYmVkL1JLZkNhQ0NLX2tJ",
    "episode" : 11,
    "kind" : "оригинал",
    "language" : "original",
    "author" : ""
  }, {
    "id" : 1897829,
    "url" : "aHR0cDovL3lvdXR1YmUuY29tL2VtYmVkLzZoSW5DaGt1Nm5B",
    "episode" : 12,
    "kind" : "оригинал",
    "language" : "original",
    "author" : ""
  }, {
    "id" : 1897830,
    "url" : "aHR0cDovL3lvdXR1YmUuY29tL2VtYmVkL3JfUzNHbWFLMmxF",
    "episode" : 13,
    "kind" : "оригинал",
    "language" : "original",
    "author" : ""
  }, {
    "id" : 1897831,
    "url" : "aHR0cDovL3lvdXR1YmUuY29tL2VtYmVkL3NmRmoweGlhUnJn",
    "episode" : 14,
    "kind" : "оригинал",
    "language" : "original",
    "author" : ""
  }, {
    "id" : 1897832,
    "url" : "aHR0cDovL3lvdXR1YmUuY29tL2VtYmVkL181WlVvRU1pUHNn",
    "episode" : 15,
    "kind" : "оригинал",
    "language" : "original",
    "author" : ""
  }, {
    "id" : 1897833,
    "url" : "aHR0cDovL3lvdXR1YmUuY29tL2VtYmVkLzA1YXYxVXA0Wldv",
    "episode" : 16,
    "kind" : "оригинал",
    "language" : "original",
    "author" : ""
  }, {
    "id" : 1897834,
    "url" : "aHR0cDovL3lvdXR1YmUuY29tL2VtYmVkL3JQdFo0aDhCbzBV",
    "episode" : 17,
    "kind" : "оригинал",
    "language" : "original",
    "author" : ""
  }, {
    "id" : 1897835,
    "url" : "aHR0cDovL3lvdXR1YmUuY29tL2VtYmVkL2tCSUFPMl92MnFZ",
    "episode" : 18,
    "kind" : "оригинал",
    "language" : "original",
    "author" : ""
  }, {
    "id" : 1897836,
    "url" : "aHR0cDovL3lvdXR1YmUuY29tL2VtYmVkLzd3U2pzM3lDcHNz",
    "episode" : 19,
    "kind" : "оригинал",
    "language" : "original",
    "author" : ""
  }, {
    "id" : 1897837,
    "url" : "aHR0cDovL3lvdXR1YmUuY29tL2VtYmVkL1MweU1MWWZiaE5F",
    "episode" : 20,
    "kind" : "оригинал",
    "language" : "original",
    "author" : ""
  }, {
    "id" : 1897839,
    "url" : "aHR0cDovL3lvdXR1YmUuY29tL2VtYmVkL0VzbHdfNDUxMXlV",
    "episode" : 21,
    "kind" : "оригинал",
    "language" : "original",
    "author" : ""
  }, {
    "id" : 1897840,
    "url" : "aHR0cDovL3lvdXR1YmUuY29tL2VtYmVkL1BkbEhHckx1cEo4",
    "episode" : 22,
    "kind" : "оригинал",
    "language" : "original",
    "author" : ""
  }, {
    "id" : 1897841,
    "url" : "aHR0cDovL3lvdXR1YmUuY29tL2VtYmVkL2wtVGMzaHBZY1dF",
    "episode" : 23,
    "kind" : "оригинал",
    "language" : "original",
    "author" : ""
  }, {
    "id" : 1897842,
    "url" : "aHR0cDovL3lvdXR1YmUuY29tL2VtYmVkL0otWWF4Ym5NYXR3",
    "episode" : 24,
    "kind" : "оригинал",
    "language" : "original",
    "author" : ""
  }, {
    "id" : 1897844,
    "url" : "aHR0cDovL3lvdXR1YmUuY29tL2VtYmVkL1pmZ25FSjFuMTk0",
    "episode" : 25,
    "kind" : "оригинал",
    "language" : "original",
    "author" : ""
  }, {
    "id" : 1897845,
    "url" : "aHR0cDovL3lvdXR1YmUuY29tL2VtYmVkL3VfZTVFQkdoZ29Z",
    "episode" : 26,
    "kind" : "оригинал",
    "language" : "original",
    "author" : ""
  }, {
    "id" : 1897846,
    "url" : "aHR0cDovL3lvdXR1YmUuY29tL2VtYmVkL1hscG5XT1lBc1pB",
    "episode" : 27,
    "kind" : "оригинал",
    "language" : "original",
    "author" : ""
  }, {
    "id" : 1897847,
    "url" : "aHR0cDovL3lvdXR1YmUuY29tL2VtYmVkL0REeUVFUExXbW5N",
    "episode" : 28,
    "kind" : "оригинал",
    "language" : "original",
    "author" : ""
  }, {
    "id" : 1897849,
    "url" : "aHR0cDovL3lvdXR1YmUuY29tL2VtYmVkL2NpX0JCbjNNdzlF",
    "episode" : 29,
    "kind" : "оригинал",
    "language" : "original",
    "author" : ""
  }, {
    "id" : 1897850,
    "url" : "aHR0cDovL3lvdXR1YmUuY29tL2VtYmVkLzFvaXh0bmIyYllZ",
    "episode" : 30,
    "kind" : "оригинал",
    "language" : "original",
    "author" : ""
  }, {
    "id" : 1897852,
    "url" : "aHR0cDovL3lvdXR1YmUuY29tL2VtYmVkL0hRRmVuRW0zeDNB",
    "episode" : 31,
    "kind" : "оригинал",
    "language" : "original",
    "author" : ""
  }, {
    "id" : 1897853,
    "url" : "aHR0cDovL3lvdXR1YmUuY29tL2VtYmVkL0JDYm1DNFFLbXZB",
    "episode" : 32,
    "kind" : "оригинал",
    "language" : "original",
    "author" : ""
  }, {
    "id" : 1897854,
    "url" : "aHR0cDovL3lvdXR1YmUuY29tL2VtYmVkL1BpUXFXRmlBS3Nj",
    "episode" : 33,
    "kind" : "оригинал",
    "language" : "original",
    "author" : ""
  }, {
    "id" : 1897855,
    "url" : "aHR0cDovL3lvdXR1YmUuY29tL2VtYmVkLzlqS1VEampDTDNZ",
    "episode" : 34,
    "kind" : "оригинал",
    "language" : "original",
    "author" : ""
  }, {
    "id" : 1897857,
    "url" : "aHR0cDovL3lvdXR1YmUuY29tL2VtYmVkL045U011ZjhUYURN",
    "episode" : 35,
    "kind" : "оригинал",
    "language" : "original",
    "author" : ""
  }, {
    "id" : 1897858,
    "url" : "aHR0cDovL3lvdXR1YmUuY29tL2VtYmVkL0ZoWHJKSTVvT09n",
    "episode" : 36,
    "kind" : "оригинал",
    "language" : "original",
    "author" : ""
  }, {
    "id" : 1897859,
    "url" : "aHR0cDovL3lvdXR1YmUuY29tL2VtYmVkL2doOVJpYnBZRll3",
    "episode" : 37,
    "kind" : "оригинал",
    "language" : "original",
    "author" : ""
  }, {
    "id" : 1897860,
    "url" : "aHR0cDovL3lvdXR1YmUuY29tL2VtYmVkL3RaZVVwTHdNX0dF",
    "episode" : 38,
    "kind" : "оригинал",
    "language" : "original",
    "author" : ""
  }, {
    "id" : 1897861,
    "url" : "aHR0cDovL3lvdXR1YmUuY29tL2VtYmVkL2NYZ1d1YkpmNW1F",
    "episode" : 39,
    "kind" : "оригинал",
    "language" : "original",
    "author" : ""
  }, {
    "id" : 1897862,
    "url" : "aHR0cDovL3lvdXR1YmUuY29tL2VtYmVkL1Q1RGlXdG0yc0hn",
    "episode" : 40,
    "kind" : "оригинал",
    "language" : "original",
    "author" : ""
  }, {
    "id" : 1897863,
    "url" : "aHR0cDovL3lvdXR1YmUuY29tL2VtYmVkL2VmaTk4aEo4aDVF",
    "episode" : 41,
    "kind" : "оригинал",
    "language" : "original",
    "author" : ""
  }, {
    "id" : 1897864,
    "url" : "aHR0cDovL3lvdXR1YmUuY29tL2VtYmVkL3dZRlF4ZkRISkU4",
    "episode" : 42,
    "kind" : "оригинал",
    "language" : "original",
    "author" : ""
  }, {
    "id" : 1897865,
    "url" : "aHR0cDovL3lvdXR1YmUuY29tL2VtYmVkL0F1d1hUdDlFWHFF",
    "episode" : 43,
    "kind" : "оригинал",
    "language" : "original",
    "author" : ""
  }, {
    "id" : 1897866,
    "url" : "aHR0cDovL3lvdXR1YmUuY29tL2VtYmVkL004ZHozZldXSk5v",
    "episode" : 44,
    "kind" : "оригинал",
    "language" : "original",
    "author" : ""
  }, {
    "id" : 1897867,
    "url" : "aHR0cDovL3lvdXR1YmUuY29tL2VtYmVkL2xWdVhfWUFmR0VF",
    "episode" : 45,
    "kind" : "оригинал",
    "language" : "original",
    "author" : ""
  }, {
    "id" : 1897868,
    "url" : "aHR0cDovL3lvdXR1YmUuY29tL2VtYmVkL3BJZTVCbkZGcWlV",
    "episode" : 46,
    "kind" : "оригинал",
    "language" : "original",
    "author" : ""
  }, {
    "id" : 1897869,
    "url" : "aHR0cDovL3lvdXR1YmUuY29tL2VtYmVkLzRFSDdNaGpyZ3o0",
    "episode" : 47,
    "kind" : "оригинал",
    "language" : "original",
    "author" : ""
  }, {
    "id" : 1897870,
    "url" : "aHR0cDovL3lvdXR1YmUuY29tL2VtYmVkL0w1TjZQSWJRR3lv",
    "episode" : 48,
    "kind" : "оригинал",
    "language" : "original",
    "author" : ""
  }, {
    "id" : 1897871,
    "url" : "aHR0cDovL3lvdXR1YmUuY29tL2VtYmVkLzItQmxiLUREemVv",
    "episode" : 49,
    "kind" : "оригинал",
    "language" : "original",
    "author" : ""
  }, {
    "id" : 1897872,
    "url" : "aHR0cDovL3lvdXR1YmUuY29tL2VtYmVkLy1qQklIX1V6aTQw",
    "episode" : 50,
    "kind" : "оригинал",
    "language" : "original",
    "author" : ""
  }, {
    "id" : 1897874,
    "url" : "aHR0cDovL3lvdXR1YmUuY29tL2VtYmVkLzZUMHQ0cXM1V0dj",
    "episode" : 51,
    "kind" : "оригинал",
    "language" : "original",
    "author" : ""
  }, {
    "id" : 1897875,
    "url" : "aHR0cDovL3lvdXR1YmUuY29tL2VtYmVkLzBzNEJQSVV4d3kw",
    "episode" : 52,
    "kind" : "оригинал",
    "language" : "original",
    "author" : ""
  }, {
    "id" : 1897876,
    "url" : "aHR0cDovL3lvdXR1YmUuY29tL2VtYmVkL2EyaWdJcllfSWI4",
    "episode" : 53,
    "kind" : "оригинал",
    "language" : "original",
    "author" : ""
  }, {
    "id" : 1897877,
    "url" : "aHR0cDovL3lvdXR1YmUuY29tL2VtYmVkL0QzZ3Q0dTFhVEhF",
    "episode" : 54,
    "kind" : "оригинал",
    "language" : "original",
    "author" : ""
  }, {
    "id" : 1897878,
    "url" : "aHR0cDovL3lvdXR1YmUuY29tL2VtYmVkL2p2VTVDTVNYYUNv",
    "episode" : 55,
    "kind" : "оригинал",
    "language" : "original",
    "author" : ""
  }, {
    "id" : 1897879,
    "url" : "aHR0cDovL3lvdXR1YmUuY29tL2VtYmVkL0U4Z2VXQjVKM1ZR",
    "episode" : 56,
    "kind" : "оригинал",
    "language" : "original",
    "author" : ""
  }, {
    "id" : 1897880,
    "url" : "aHR0cDovL3lvdXR1YmUuY29tL2VtYmVkL240cUEwdWJtUTdV",
    "episode" : 57,
    "kind" : "оригинал",
    "language" : "original",
    "author" : ""
  }, {
    "id" : 1897881,
    "url" : "aHR0cDovL3lvdXR1YmUuY29tL2VtYmVkL0hGOEJmY2VEZ19F",
    "episode" : 58,
    "kind" : "оригинал",
    "language" : "original",
    "author" : ""
  }, {
    "id" : 1897882,
    "url" : "aHR0cDovL3lvdXR1YmUuY29tL2VtYmVkLzdYTDJwQmo1MWFv",
    "episode" : 59,
    "kind" : "оригинал",
    "language" : "original",
    "author" : ""
  }, {
    "id" : 1897883,
    "url" : "aHR0cDovL3lvdXR1YmUuY29tL2VtYmVkL0FvZWQxQ3ZDSmo4",
    "episode" : 60,
    "kind" : "оригинал",
    "language" : "original",
    "author" : ""
  }, {
    "id" : 1897885,
    "url" : "aHR0cDovL3lvdXR1YmUuY29tL2VtYmVkL0NqdTliVUhQeTJB",
    "episode" : 61,
    "kind" : "оригинал",
    "language" : "original",
    "author" : ""
  }, {
    "id" : 1897886,
    "url" : "aHR0cDovL3lvdXR1YmUuY29tL2VtYmVkL0ZWZVRTRTkwRW1R",
    "episode" : 62,
    "kind" : "оригинал",
    "language" : "original",
    "author" : ""
  }, {
    "id" : 1897887,
    "url" : "aHR0cDovL3lvdXR1YmUuY29tL2VtYmVkL1habGdaX1A5dVRJ",
    "episode" : 63,
    "kind" : "оригинал",
    "language" : "original",
    "author" : ""
  }, {
    "id" : 1897888,
    "url" : "aHR0cDovL3lvdXR1YmUuY29tL2VtYmVkL1V3QkkyT01NNVow",
    "episode" : 64,
    "kind" : "оригинал",
    "language" : "original",
    "author" : ""
  }, {
    "id" : 1897889,
    "url" : "aHR0cDovL3lvdXR1YmUuY29tL2VtYmVkL2ttWUo3cHVPck80",
    "episode" : 65,
    "kind" : "оригинал",
    "language" : "original",
    "author" : ""
  }, {
    "id" : 1897890,
    "url" : "aHR0cDovL3lvdXR1YmUuY29tL2VtYmVkL0h5WURJV2dEc0lz",
    "episode" : 66,
    "kind" : "оригинал",
    "language" : "original",
    "author" : ""
  }, {
    "id" : 1897891,
    "url" : "aHR0cDovL3lvdXR1YmUuY29tL2VtYmVkLzV3THVLMDF1d3Yw",
    "episode" : 67,
    "kind" : "оригинал",
    "language" : "original",
    "author" : ""
  }, {
    "id" : 1897892,
    "url" : "aHR0cDovL3lvdXR1YmUuY29tL2VtYmVkL1pGd19lUGl4XzM4",
    "episode" : 68,
    "kind" : "оригинал",
    "language" : "original",
    "author" : ""
  }, {
    "id" : 1897893,
    "url" : "aHR0cDovL3lvdXR1YmUuY29tL2VtYmVkL0E5ZWlUb0NsdmVN",
    "episode" : 69,
    "kind" : "оригинал",
    "language" : "original",
    "author" : ""
  }, {
    "id" : 1897894,
    "url" : "aHR0cDovL3lvdXR1YmUuY29tL2VtYmVkL2h0YVFaVTBQRFRv",
    "episode" : 70,
    "kind" : "оригинал",
    "language" : "original",
    "author" : ""
  }, {
    "id" : 1897895,
    "url" : "aHR0cDovL3lvdXR1YmUuY29tL2VtYmVkL3RoQnUwVVh6MmYw",
    "episode" : 71,
    "kind" : "оригинал",
    "language" : "original",
    "author" : ""
  }, {
    "id" : 1897896,
    "url" : "aHR0cDovL3lvdXR1YmUuY29tL2VtYmVkL3ZhaUtKUk9ONGFn",
    "episode" : 72,
    "kind" : "оригинал",
    "language" : "original",
    "author" : ""
  }, {
    "id" : 1897897,
    "url" : "aHR0cDovL3lvdXR1YmUuY29tL2VtYmVkL2pXZGRTbGY3dk9J",
    "episode" : 73,
    "kind" : "оригинал",
    "language" : "original",
    "author" : ""
  }, {
    "id" : 1897898,
    "url" : "aHR0cDovL3lvdXR1YmUuY29tL2VtYmVkL29udzVDV3BkTV9J",
    "episode" : 74,
    "kind" : "оригинал",
    "language" : "original",
    "author" : ""
  }, {
    "id" : 1897899,
    "url" : "aHR0cDovL3lvdXR1YmUuY29tL2VtYmVkL0xmZ0w1b1NuSDQ0",
    "episode" : 75,
    "kind" : "оригинал",
    "language" : "original",
    "author" : ""
  }, {
    "id" : 1897900,
    "url" : "aHR0cDovL3lvdXR1YmUuY29tL2VtYmVkL3dlb2x2VDhYTEpv",
    "episode" : 76,
    "kind" : "оригинал",
    "language" : "original",
    "author" : ""
  }, {
    "id" : 1897901,
    "url" : "aHR0cDovL3lvdXR1YmUuY29tL2VtYmVkL210VTRHRzNZVWVZ",
    "episode" : 77,
    "kind" : "оригинал",
    "language" : "original",
    "author" : ""
  }, {
    "id" : 1897902,
    "url" : "aHR0cDovL3lvdXR1YmUuY29tL2VtYmVkL0pFY2Y3bzFHdlJF",
    "episode" : 78,
    "kind" : "оригинал",
    "language" : "original",
    "author" : ""
  }, {
    "id" : 1897904,
    "url" : "aHR0cDovL3lvdXR1YmUuY29tL2VtYmVkL0RLVWtEX0w4cm9v",
    "episode" : 79,
    "kind" : "оригинал",
    "language" : "original",
    "author" : ""
  }, {
    "id" : 1897905,
    "url" : "aHR0cDovL3lvdXR1YmUuY29tL2VtYmVkL0R4T2NOa1RnVmdv",
    "episode" : 80,
    "kind" : "оригинал",
    "language" : "original",
    "author" : ""
  }, {
    "id" : 1897906,
    "url" : "aHR0cDovL3lvdXR1YmUuY29tL2VtYmVkL0ZyM2VCLUZpcEJ3",
    "episode" : 81,
    "kind" : "оригинал",
    "language" : "original",
    "author" : ""
  }, {
    "id" : 1897907,
    "url" : "aHR0cDovL3lvdXR1YmUuY29tL2VtYmVkL2dCLXlvek9XVDdZ",
    "episode" : 82,
    "kind" : "оригинал",
    "language" : "original",
    "author" : ""
  }, {
    "id" : 1897908,
    "url" : "aHR0cDovL3lvdXR1YmUuY29tL2VtYmVkL3BseDhNQTF6WVN3",
    "episode" : 83,
    "kind" : "оригинал",
    "language" : "original",
    "author" : ""
  }, {
    "id" : 1897909,
    "url" : "aHR0cDovL3lvdXR1YmUuY29tL2VtYmVkL2Z4V2ZFdDZwdXhj",
    "episode" : 84,
    "kind" : "оригинал",
    "language" : "original",
    "author" : ""
  }, {
    "id" : 1897910,
    "url" : "aHR0cDovL3lvdXR1YmUuY29tL2VtYmVkL0ZMZ2cyMzBoRHY4",
    "episode" : 85,
    "kind" : "оригинал",
    "language" : "original",
    "author" : ""
  }, {
    "id" : 1897911,
    "url" : "aHR0cDovL3lvdXR1YmUuY29tL2VtYmVkL2xDcTAxbVR2WnVV",
    "episode" : 86,
    "kind" : "оригинал",
    "language" : "original",
    "author" : ""
  }, {
    "id" : 1897912,
    "url" : "aHR0cDovL3lvdXR1YmUuY29tL2VtYmVkL2Fva1o2QWZuVkkw",
    "episode" : 87,
    "kind" : "оригинал",
    "language" : "original",
    "author" : ""
  }, {
    "id" : 1897913,
    "url" : "aHR0cDovL3lvdXR1YmUuY29tL2VtYmVkL0JIWmlzUVZCWUpF",
    "episode" : 88,
    "kind" : "оригинал",
    "language" : "original",
    "author" : ""
  }, {
    "id" : 1897914,
    "url" : "aHR0cDovL3lvdXR1YmUuY29tL2VtYmVkLzE0eENlaXAtU1Jj",
    "episode" : 89,
    "kind" : "оригинал",
    "language" : "original",
    "author" : ""
  }, {
    "id" : 1897916,
    "url" : "aHR0cDovL3lvdXR1YmUuY29tL2VtYmVkLzJuR29MQ1B5d1Zz",
    "episode" : 90,
    "kind" : "оригинал",
    "language" : "original",
    "author" : ""
  }, {
    "id" : 1897917,
    "url" : "aHR0cDovL3lvdXR1YmUuY29tL2VtYmVkL1JaeG1oRFRpeHJn",
    "episode" : 91,
    "kind" : "оригинал",
    "language" : "original",
    "author" : ""
  }, {
    "id" : 1897918,
    "url" : "aHR0cDovL3lvdXR1YmUuY29tL2VtYmVkLzBrek8ydXlGdjVz",
    "episode" : 92,
    "kind" : "оригинал",
    "language" : "original",
    "author" : ""
  }, {
    "id" : 1897919,
    "url" : "aHR0cDovL3lvdXR1YmUuY29tL2VtYmVkL1oxeHZTaGxmajdz",
    "episode" : 93,
    "kind" : "оригинал",
    "language" : "original",
    "author" : ""
  }, {
    "id" : 1897920,
    "url" : "aHR0cDovL3lvdXR1YmUuY29tL2VtYmVkL3JjMmh5ellJTGpr",
    "episode" : 94,
    "kind" : "оригинал",
    "language" : "original",
    "author" : ""
  }, {
    "id" : 1897921,
    "url" : "aHR0cDovL3lvdXR1YmUuY29tL2VtYmVkL05rTEpraEQ1R09B",
    "episode" : 95,
    "kind" : "оригинал",
    "language" : "original",
    "author" : ""
  }, {
    "id" : 1897922,
    "url" : "aHR0cDovL3lvdXR1YmUuY29tL2VtYmVkLzdHbXlfMjh1Q1lZ",
    "episode" : 96,
    "kind" : "оригинал",
    "language" : "original",
    "author" : ""
  }, {
    "id" : 1897923,
    "url" : "aHR0cDovL3lvdXR1YmUuY29tL2VtYmVkL3RVS3NBS21YM2Vz",
    "episode" : 97,
    "kind" : "оригинал",
    "language" : "original",
    "author" : ""
  }, {
    "id" : 1897924,
    "url" : "aHR0cDovL3lvdXR1YmUuY29tL2VtYmVkL3FQbndQWXdVRHpF",
    "episode" : 98,
    "kind" : "оригинал",
    "language" : "original",
    "author" : ""
  }, {
    "id" : 1897925,
    "url" : "aHR0cDovL3lvdXR1YmUuY29tL2VtYmVkLzhBTExkbmRINHZR",
    "episode" : 99,
    "kind" : "оригинал",
    "language" : "original",
    "author" : ""
  }, {
    "id" : 1897926,
    "url" : "aHR0cDovL3lvdXR1YmUuY29tL2VtYmVkL3V6aHV6SjJYUUpN",
    "episode" : 100,
    "kind" : "оригинал",
    "language" : "original",
    "author" : ""
  }, {
    "id" : 1897927,
    "url" : "aHR0cDovL3lvdXR1YmUuY29tL2VtYmVkL0RsRi0yVDlSUk13",
    "episode" : 101,
    "kind" : "оригинал",
    "language" : "original",
    "author" : ""
  }, {
    "id" : 1897929,
    "url" : "aHR0cDovL3lvdXR1YmUuY29tL2VtYmVkL3dQbHNSeUhqVTlr",
    "episode" : 102,
    "kind" : "оригинал",
    "language" : "original",
    "author" : ""
  }, {
    "id" : 1897930,
    "url" : "aHR0cDovL3lvdXR1YmUuY29tL2VtYmVkL1NjNHVKR3hLUURz",
    "episode" : 103,
    "kind" : "оригинал",
    "language" : "original",
    "author" : ""
  }, {
    "id" : 1897931,
    "url" : "aHR0cDovL3lvdXR1YmUuY29tL2VtYmVkL2J6V1paMlNKUGNF",
    "episode" : 104,
    "kind" : "оригинал",
    "language" : "original",
    "author" : ""
  }, {
    "id" : 1897932,
    "url" : "aHR0cDovL3lvdXR1YmUuY29tL2VtYmVkL1ZtU1VDX2plVmNF",
    "episode" : 105,
    "kind" : "оригинал",
    "language" : "original",
    "author" : ""
  }, {
    "id" : 1897933,
    "url" : "aHR0cDovL3lvdXR1YmUuY29tL2VtYmVkL2diNXlaMkZfSjhN",
    "episode" : 106,
    "kind" : "оригинал",
    "language" : "original",
    "author" : ""
  }, {
    "id" : 1897935,
    "url" : "aHR0cDovL3lvdXR1YmUuY29tL2VtYmVkLzVXVVE5R2pyWjNB",
    "episode" : 107,
    "kind" : "оригинал",
    "language" : "original",
    "author" : ""
  }, {
    "id" : 1897936,
    "url" : "aHR0cDovL3lvdXR1YmUuY29tL2VtYmVkL0NNVUZ2N2ZyWWgw",
    "episode" : 108,
    "kind" : "оригинал",
    "language" : "original",
    "author" : ""
  }, {
    "id" : 1897937,
    "url" : "aHR0cDovL3lvdXR1YmUuY29tL2VtYmVkL1BHLUotdUlVU0tn",
    "episode" : 109,
    "kind" : "оригинал",
    "language" : "original",
    "author" : ""
  }, {
    "id" : 1897938,
    "url" : "aHR0cDovL3lvdXR1YmUuY29tL2VtYmVkL2JRTDJ0cXpPTTRB",
    "episode" : 110,
    "kind" : "оригинал",
    "language" : "original",
    "author" : ""
  }, {
    "id" : 1897940,
    "url" : "aHR0cDovL3lvdXR1YmUuY29tL2VtYmVkLzFPR3B2UnNkYUJB",
    "episode" : 111,
    "kind" : "оригинал",
    "language" : "original",
    "author" : ""
  }, {
    "id" : 1897941,
    "url" : "aHR0cDovL3lvdXR1YmUuY29tL2VtYmVkLzh2djNlOExlbWln",
    "episode" : 112,
    "kind" : "оригинал",
    "language" : "original",
    "author" : ""
  }, {
    "id" : 1897942,
    "url" : "aHR0cDovL3lvdXR1YmUuY29tL2VtYmVkLzZHb2tNSWpZc1M4",
    "episode" : 113,
    "kind" : "оригинал",
    "language" : "original",
    "author" : ""
  }, {
    "id" : 1897943,
    "url" : "aHR0cDovL3lvdXR1YmUuY29tL2VtYmVkL1JkRk01MHl2MHg0",
    "episode" : 114,
    "kind" : "оригинал",
    "language" : "original",
    "author" : ""
  }, {
    "id" : 1897944,
    "url" : "aHR0cDovL3lvdXR1YmUuY29tL2VtYmVkL2xPZXhFNEtiRUJr",
    "episode" : 115,
    "kind" : "оригинал",
    "language" : "original",
    "author" : ""
  }, {
    "id" : 1897946,
    "url" : "aHR0cDovL3lvdXR1YmUuY29tL2VtYmVkL2lndVkyTHZHMnVj",
    "episode" : 116,
    "kind" : "оригинал",
    "language" : "original",
    "author" : ""
  }, {
    "id" : 1897947,
    "url" : "aHR0cDovL3lvdXR1YmUuY29tL2VtYmVkL0FLQnc4YTNCLW44",
    "episode" : 117,
    "kind" : "оригинал",
    "language" : "original",
    "author" : ""
  }, {
    "id" : 1897948,
    "url" : "aHR0cDovL3lvdXR1YmUuY29tL2VtYmVkL0NrMGhTRHkzNlpR",
    "episode" : 118,
    "kind" : "оригинал",
    "language" : "original",
    "author" : ""
  }, {
    "id" : 1897949,
    "url" : "aHR0cDovL3lvdXR1YmUuY29tL2VtYmVkL3g5UGNQR2VTSnZR",
    "episode" : 119,
    "kind" : "оригинал",
    "language" : "original",
    "author" : ""
  }, {
    "id" : 1897950,
    "url" : "aHR0cDovL3lvdXR1YmUuY29tL2VtYmVkL09YMmZMVGJCdkJr",
    "episode" : 120,
    "kind" : "оригинал",
    "language" : "original",
    "author" : ""
  }, {
    "id" : 1897951,
    "url" : "aHR0cDovL3lvdXR1YmUuY29tL2VtYmVkL1ctNmVnZnhDVXJR",
    "episode" : 121,
    "kind" : "оригинал",
    "language" : "original",
    "author" : ""
  }, {
    "id" : 1897952,
    "url" : "aHR0cDovL3lvdXR1YmUuY29tL2VtYmVkLzFSZHNHUGpCVndB",
    "episode" : 122,
    "kind" : "оригинал",
    "language" : "original",
    "author" : ""
  }, {
    "id" : 1897953,
    "url" : "aHR0cDovL3lvdXR1YmUuY29tL2VtYmVkLzFuS2pLUC1aMnVN",
    "episode" : 123,
    "kind" : "оригинал",
    "language" : "original",
    "author" : ""
  }, {
    "id" : 1897954,
    "url" : "aHR0cDovL3lvdXR1YmUuY29tL2VtYmVkL3p2SndMY3FITmtB",
    "episode" : 124,
    "kind" : "оригинал",
    "language" : "original",
    "author" : ""
  }, {
    "id" : 1897956,
    "url" : "aHR0cDovL3lvdXR1YmUuY29tL2VtYmVkL0ZidlVlVG5YdzlN",
    "episode" : 125,
    "kind" : "оригинал",
    "language" : "original",
    "author" : ""
  } ]
}