{
  "items" : [ {
    "id" : 1754114,
    "url" : "aHR0cDovL3lvdXR1YmUuY29tL2VtYmVkL3Bnc1NjZktNYUNv",
    "episode" : 1,
    "kind" : "оригинал",
    "language" : "original",
    "author" : ""
  }, {
    "id" : 1754115,
    "url" : "aHR0cDovL3lvdXR1YmUuY29tL2VtYmVkL0R6SnNyYTFtcjFz",
    "episode" : 2,
    "kind" : "оригинал",
    "language" : "original",
    "author" : ""
  }, {
    "id" : 1754116,
    "url" : "aHR0cDovL3lvdXR1YmUuY29tL2VtYmVkLzJiQ0p3aXhGTGo4",
    "episode" : 3,
    "kind" : "оригинал",
    "language" : "original",
    "author" : ""
  }, {
    "id" : 1754117,
    "url" : "aHR0cDovL3lvdXR1YmUuY29tL2VtYmVkL1kyRmRlY0FQbW1J",
    "episode" : 4,
    "kind" : "оригинал",
    "language" : "original",
    "author" : ""
  } ]
}