{
  "items" : [ {
    "id" : 1506780,
    "url" : "aHR0cDovL3lvdXR1YmUuY29tL2VtYmVkL2JwcXJESGhxeWJ3",
    "episode" : 1,
    "kind" : "оригинал",
    "language" : "original",
    "author" : ""
  }, {
    "id" : 1506781,
    "url" : "aHR0cDovL3lvdXR1YmUuY29tL2VtYmVkL1JoM1NibUtQQzVB",
    "episode" : 2,
    "kind" : "оригинал",
    "language" : "original",
    "author" : ""
  }, {
    "id" : 1506782,
    "url" : "aHR0cDovL3lvdXR1YmUuY29tL2VtYmVkL3RTcnJqNHZYbzdv",
    "episode" : 7,
    "kind" : "оригинал",
    "language" : "original",
    "author" : ""
  }, {
    "id" : 1506783,
    "url" : "aHR0cDovL3lvdXR1YmUuY29tL2VtYmVkL1dBNk5IWFBaTlZV",
    "episode" : 8,
    "kind" : "оригинал",
    "language" : "original",
    "author" : ""
  }, {
    "id" : 1506784,
    "url" : "aHR0cDovL3lvdXR1YmUuY29tL2VtYmVkL2RLLXZ2YlhQQUs4",
    "episode" : 10,
    "kind" : "оригинал",
    "language" : "original",
    "author" : ""
  }, {
    "id" : 1506785,
    "url" : "aHR0cDovL3lvdXR1YmUuY29tL2VtYmVkL2RveE9CajhlSnVn",
    "episode" : 12,
    "kind" : "оригинал",
    "language" : "original",
    "author" : ""
  } ]
}