{
  "items" : [ {
    "id" : 1661105,
    "url" : "aHR0cDovL3lvdXR1YmUuY29tL2VtYmVkL1d4R1hTYU95UDJ3",
    "episode" : 1,
    "kind" : "оригинал",
    "language" : "original",
    "author" : ""
  }, {
    "id" : 1661106,
    "url" : "aHR0cDovL3lvdXR1YmUuY29tL2VtYmVkL29MOXpYMXJXSVBF",
    "episode" : 2,
    "kind" : "оригинал",
    "language" : "original",
    "author" : ""
  }, {
    "id" : 1661107,
    "url" : "aHR0cDovL3lvdXR1YmUuY29tL2VtYmVkLzJmR1hkYXoyR0Jv",
    "episode" : 3,
    "kind" : "оригинал",
    "language" : "original",
    "author" : ""
  }, {
    "id" : 1661108,
    "url" : "aHR0cDovL3lvdXR1YmUuY29tL2VtYmVkL3BJNVREWlZrSkxF",
    "episode" : 4,
    "kind" : "оригинал",
    "language" : "original",
    "author" : ""
  }, {
    "id" : 1661109,
    "url" : "aHR0cDovL3lvdXR1YmUuY29tL2VtYmVkL1NJeVNPV2xTdURv",
    "episode" : 5,
    "kind" : "оригинал",
    "language" : "original",
    "author" : ""
  }, {
    "id" : 1661110,
    "url" : "aHR0cDovL3lvdXR1YmUuY29tL2VtYmVkLzJ0bDUzUzFVclln",
    "episode" : 6,
    "kind" : "оригинал",
    "language" : "original",
    "author" : ""
  }, {
    "id" : 1661111,
    "url" : "aHR0cDovL3lvdXR1YmUuY29tL2VtYmVkLzlGdVpUUmpsVlB3",
    "episode" : 7,
    "kind" : "оригинал",
    "language" : "original",
    "author" : ""
  }, {
    "id" : 1661112,
    "url" : "aHR0cDovL3lvdXR1YmUuY29tL2VtYmVkL0J3N2FkbjZoUGNR",
    "episode" : 8,
    "kind" : "оригинал",
    "language" : "original",
    "author" : ""
  }, {
    "id" : 1661113,
    "url" : "aHR0cDovL3lvdXR1YmUuY29tL2VtYmVkL1UyR3owR0NYeEJF",
    "episode" : 9,
    "kind" : "оригинал",
    "language" : "original",
    "author" : ""
  }, {
    "id" : 1661114,
    "url" : "aHR0cDovL3lvdXR1YmUuY29tL2VtYmVkL1V6X2YxVDRwMS1B",
    "episode" : 10,
    "kind" : "оригинал",
    "language" : "original",
    "author" : ""
  }, {
    "id" : 1661115,
    "url" : "aHR0cDovL3lvdXR1YmUuY29tL2VtYmVkLzJSclVmOGo2Zmtn",
    "episode" : 11,
    "kind" : "оригинал",
    "language" : "original",
    "author" : ""
  }, {
    "id" : 1661116,
    "url" : "aHR0cDovL3lvdXR1YmUuY29tL2VtYmVkL0Z0Y19FaE9uSEJv",
    "episode" : 12,
    "kind" : "оригинал",
    "language" : "original",
    "author" : ""
  }, {
    "id" : 1661117,
    "url" : "aHR0cDovL3lvdXR1YmUuY29tL2VtYmVkLzN2UnpKd1VncG9B",
    "episode" : 13,
    "kind" : "оригинал",
    "language" : "original",
    "author" : ""
  }, {
    "id" : 1661118,
    "url" : "aHR0cDovL3lvdXR1YmUuY29tL2VtYmVkLzh5ZkFJWl9FenhV",
    "episode" : 14,
    "kind" : "оригинал",
    "language" : "original",
    "author" : ""
  }, {
    "id" : 1661119,
    "url" : "aHR0cDovL3lvdXR1YmUuY29tL2VtYmVkL0RYdDk2TGZUcXdV",
    "episode" : 15,
    "kind" : "оригинал",
    "language" : "original",
    "author" : ""
  }, {
    "id" : 1661120,
    "url" : "aHR0cDovL3lvdXR1YmUuY29tL2VtYmVkL3pXN1gtQmpIQ2hZ",
    "episode" : 16,
    "kind" : "оригинал",
    "language" : "original",
    "author" : ""
  }, {
    "id" : 1661121,
    "url" : "aHR0cDovL3lvdXR1YmUuY29tL2VtYmVkL0tESXRJS242WEJV",
    "episode" : 17,
    "kind" : "оригинал",
    "language" : "original",
    "author" : ""
  }, {
    "id" : 1661122,
    "url" : "aHR0cDovL3lvdXR1YmUuY29tL2VtYmVkLzVvdGxESEluMzlZ",
    "episode" : 18,
    "kind" : "оригинал",
    "language" : "original",
    "author" : ""
  }, {
    "id" : 1661123,
    "url" : "aHR0cDovL3lvdXR1YmUuY29tL2VtYmVkLzIwVHpaOUg1allB",
    "episode" : 19,
    "kind" : "оригинал",
    "language" : "original",
    "author" : ""
  }, {
    "id" : 1661124,
    "url" : "aHR0cDovL3lvdXR1YmUuY29tL2VtYmVkL0tIMjFxRzkya1dv",
    "episode" : 20,
    "kind" : "оригинал",
    "language" : "original",
    "author" : ""
  }, {
    "id" : 1661125,
    "url" : "aHR0cDovL3lvdXR1YmUuY29tL2VtYmVkLzVXUUhSZTV5dkhz",
    "episode" : 21,
    "kind" : "оригинал",
    "language" : "original",
    "author" : ""
  }, {
    "id" : 1661126,
    "url" : "aHR0cDovL3lvdXR1YmUuY29tL2VtYmVkL0dsZEVUN0dPUTQ0",
    "episode" : 22,
    "kind" : "оригинал",
    "language" : "original",
    "author" : ""
  }, {
    "id" : 1661127,
    "url" : "aHR0cDovL3lvdXR1YmUuY29tL2VtYmVkL0FiWUVRa1dhY2w4",
    "episode" : 23,
    "kind" : "оригинал",
    "language" : "original",
    "author" : ""
  }, {
    "id" : 1661128,
    "url" : "aHR0cDovL3lvdXR1YmUuY29tL2VtYmVkLzlMMDZobDBveHY0",
    "episode" : 24,
    "kind" : "оригинал",
    "language" : "original",
    "author" : ""
  }, {
    "id" : 1661129,
    "url" : "aHR0cDovL3lvdXR1YmUuY29tL2VtYmVkL1MxWGdGOWdDNzlV",
    "episode" : 25,
    "kind" : "оригинал",
    "language" : "original",
    "author" : ""
  }, {
    "id" : 1661130,
    "url" : "aHR0cDovL3lvdXR1YmUuY29tL2VtYmVkL2NxWndZLUhVeWlV",
    "episode" : 26,
    "kind" : "оригинал",
    "language" : "original",
    "author" : ""
  }, {
    "id" : 1661131,
    "url" : "aHR0cDovL3lvdXR1YmUuY29tL2VtYmVkL0wycUVHSklaRWRr",
    "episode" : 27,
    "kind" : "оригинал",
    "language" : "original",
    "author" : ""
  }, {
    "id" : 1661132,
    "url" : "aHR0cDovL3lvdXR1YmUuY29tL2VtYmVkL001bUM1MXRxN3FF",
    "episode" : 28,
    "kind" : "оригинал",
    "language" : "original",
    "author" : ""
  }, {
    "id" : 1661133,
    "url" : "aHR0cDovL3lvdXR1YmUuY29tL2VtYmVkL2ppb0dPN3Z6LUhn",
    "episode" : 29,
    "kind" : "оригинал",
    "language" : "original",
    "author" : ""
  }, {
    "id" : 1661134,
    "url" : "aHR0cDovL3lvdXR1YmUuY29tL2VtYmVkL2VBZ2lCeWdtenc4",
    "episode" : 30,
    "kind" : "оригинал",
    "language" : "original",
    "author" : ""
  }, {
    "id" : 1661136,
    "url" : "aHR0cDovL3lvdXR1YmUuY29tL2VtYmVkL2xpZWFhSlVIU0Mw",
    "episode" : 31,
    "kind" : "оригинал",
    "language" : "original",
    "author" : ""
  }, {
    "id" : 1661137,
    "url" : "aHR0cDovL3lvdXR1YmUuY29tL2VtYmVkL0taaGVNRG80bE1z",
    "episode" : 32,
    "kind" : "оригинал",
    "language" : "original",
    "author" : ""
  }, {
    "id" : 1661138,
    "url" : "aHR0cDovL3lvdXR1YmUuY29tL2VtYmVkL1lDTExFS1BadzJB",
    "episode" : 33,
    "kind" : "оригинал",
    "language" : "original",
    "author" : ""
  }, {
    "id" : 1661139,
    "url" : "aHR0cDovL3lvdXR1YmUuY29tL2VtYmVkL2NZeWg5LUJiSkNZ",
    "episode" : 34,
    "kind" : "оригинал",
    "language" : "original",
    "author" : ""
  }, {
    "id" : 1661140,
    "url" : "aHR0cDovL3lvdXR1YmUuY29tL2VtYmVkL3gtanNGeUdYRjJv",
    "episode" : 35,
    "kind" : "оригинал",
    "language" : "original",
    "author" : ""
  }, {
    "id" : 1661141,
    "url" : "aHR0cDovL3lvdXR1YmUuY29tL2VtYmVkLy11WjZXMzNqRkRV",
    "episode" : 36,
    "kind" : "оригинал",
    "language" : "original",
    "author" : ""
  }, {
    "id" : 1661142,
    "url" : "aHR0cDovL3lvdXR1YmUuY29tL2VtYmVkL2kwMm5RWlRHUjBR",
    "episode" : 37,
    "kind" : "оригинал",
    "language" : "original",
    "author" : ""
  }, {
    "id" : 1661143,
    "url" : "aHR0cDovL3lvdXR1YmUuY29tL2VtYmVkL0lkS1o5QkVGR0dn",
    "episode" : 38,
    "kind" : "оригинал",
    "language" : "original",
    "author" : ""
  }, {
    "id" : 1661144,
    "url" : "aHR0cDovL3lvdXR1YmUuY29tL2VtYmVkLzBONDBLNWRSenhr",
    "episode" : 39,
    "kind" : "оригинал",
    "language" : "original",
    "author" : ""
  }, {
    "id" : 1661145,
    "url" : "aHR0cDovL3lvdXR1YmUuY29tL2VtYmVkL3R5N2VTN2hLU2NZ",
    "episode" : 40,
    "kind" : "оригинал",
    "language" : "original",
    "author" : ""
  }, {
    "id" : 1661148,
    "url" : "aHR0cDovL3lvdXR1YmUuY29tL2VtYmVkLzNSYk12NFdwSkhj",
    "episode" : 41,
    "kind" : "оригинал",
    "language" : "original",
    "author" : ""
  }, {
    "id" : 1661149,
    "url" : "aHR0cDovL3lvdXR1YmUuY29tL2VtYmVkL2dmcVUtU0M4a2lJ",
    "episode" : 42,
    "kind" : "оригинал",
    "language" : "original",
    "author" : ""
  }, {
    "id" : 1661150,
    "url" : "aHR0cDovL3lvdXR1YmUuY29tL2VtYmVkL1plNlR0UGNoXzNV",
    "episode" : 43,
    "kind" : "оригинал",
    "language" : "original",
    "author" : ""
  }, {
    "id" : 1661151,
    "url" : "aHR0cDovL3lvdXR1YmUuY29tL2VtYmVkL3NmQkRsQzNWT0tF",
    "episode" : 44,
    "kind" : "оригинал",
    "language" : "original",
    "author" : ""
  }, {
    "id" : 1661152,
    "url" : "aHR0cDovL3lvdXR1YmUuY29tL2VtYmVkL1hIQ2RvR3lqbFVn",
    "episode" : 45,
    "kind" : "оригинал",
    "language" : "original",
    "author" : ""
  }, {
    "id" : 1661153,
    "url" : "aHR0cDovL3lvdXR1YmUuY29tL2VtYmVkL1VBMGx3SGxXNU1J",
    "episode" : 46,
    "kind" : "оригинал",
    "language" : "original",
    "author" : ""
  }, {
    "id" : 1661154,
    "url" : "aHR0cDovL3lvdXR1YmUuY29tL2VtYmVkL0JmQ2FJVUdFZkQ0",
    "episode" : 47,
    "kind" : "оригинал",
    "language" : "original",
    "author" : ""
  }, {
    "id" : 1661156,
    "url" : "aHR0cDovL3lvdXR1YmUuY29tL2VtYmVkL1ZKbVVCMlVTVHdZ",
    "episode" : 48,
    "kind" : "оригинал",
    "language" : "original",
    "author" : ""
  }, {
    "id" : 1661157,
    "url" : "aHR0cDovL3lvdXR1YmUuY29tL2VtYmVkL0RBYzh2QndRN3Vn",
    "episode" : 49,
    "kind" : "оригинал",
    "language" : "original",
    "author" : ""
  }, {
    "id" : 1661158,
    "url" : "aHR0cDovL3lvdXR1YmUuY29tL2VtYmVkL1B6RlZuWE9ONy13",
    "episode" : 50,
    "kind" : "оригинал",
    "language" : "original",
    "author" : ""
  }, {
    "id" : 1661159,
    "url" : "aHR0cDovL3lvdXR1YmUuY29tL2VtYmVkL09WZnZuY0t1OVZF",
    "episode" : 51,
    "kind" : "оригинал",
    "language" : "original",
    "author" : ""
  }, {
    "id" : 1661160,
    "url" : "aHR0cDovL3lvdXR1YmUuY29tL2VtYmVkLzY2bjMtM1RlUjlZ",
    "episode" : 52,
    "kind" : "оригинал",
    "language" : "original",
    "author" : ""
  } ]
}