{
  "items" : [ {
    "id" : 1463416,
    "url" : "aHR0cDovL3lvdXR1YmUuY29tL2VtYmVkLzB5YWJzTW5wRXUw",
    "episode" : 1,
    "kind" : "оригинал",
    "language" : "original",
    "author" : ""
  }, {
    "id" : 1862283,
    "url" : "aHR0cDovL3lvdXR1YmUuY29tL2VtYmVkL0FCa2lqRXRxc05v",
    "episode" : 1,
    "kind" : "оригинал",
    "language" : "original",
    "author" : ""
  }, {
    "id" : 1463417,
    "url" : "aHR0cDovL3lvdXR1YmUuY29tL2VtYmVkL1JMQ0U1QnBWa3RF",
    "episode" : 2,
    "kind" : "оригинал",
    "language" : "original",
    "author" : ""
  } ]
}