{
  "items" : [ {
    "id" : 756062,
    "url" : "aHR0cDovL3lvdXR1YmUuY29tL2VtYmVkL3ZFUWVUMnd4c3Fr",
    "episode" : 1,
    "kind" : "оригинал",
    "language" : "unknown",
    "author" : ""
  }, {
    "id" : 756063,
    "url" : "aHR0cDovL3lvdXR1YmUuY29tL2VtYmVkL1k2ZkZ1QzUxaU1J",
    "episode" : 2,
    "kind" : "оригинал",
    "language" : "unknown",
    "author" : ""
  }, {
    "id" : 756064,
    "url" : "aHR0cDovL3lvdXR1YmUuY29tL2VtYmVkLzZ5TEJXRlZ2TXNz",
    "episode" : 3,
    "kind" : "оригинал",
    "language" : "unknown",
    "author" : ""
  }, {
    "id" : 756065,
    "url" : "aHR0cDovL3lvdXR1YmUuY29tL2VtYmVkL3FXY3Voai1Gd3dB",
    "episode" : 4,
    "kind" : "оригинал",
    "language" : "unknown",
    "author" : ""
  }, {
    "id" : 756066,
    "url" : "aHR0cDovL3lvdXR1YmUuY29tL2VtYmVkL0pMbzh0cTRENk1N",
    "episode" : 5,
    "kind" : "оригинал",
    "language" : "unknown",
    "author" : ""
  }, {
    "id" : 756067,
    "url" : "aHR0cDovL3lvdXR1YmUuY29tL2VtYmVkL0RpYVN0SV85a2l3",
    "episode" : 6,
    "kind" : "оригинал",
    "language" : "unknown",
    "author" : ""
  }, {
    "id" : 756068,
    "url" : "aHR0cDovL3lvdXR1YmUuY29tL2VtYmVkL2VhblBkcF9tdHFF",
    "episode" : 7,
    "kind" : "оригинал",
    "language" : "unknown",
    "author" : ""
  }, {
    "id" : 756069,
    "url" : "aHR0cDovL3lvdXR1YmUuY29tL2VtYmVkL1NfNmoza1lHLVI0",
    "episode" : 8,
    "kind" : "оригинал",
    "language" : "unknown",
    "author" : ""
  }, {
    "id" : 756070,
    "url" : "aHR0cDovL3lvdXR1YmUuY29tL2VtYmVkL0M5bzhBb2gzRnpF",
    "episode" : 9,
    "kind" : "оригинал",
    "language" : "unknown",
    "author" : ""
  }, {
    "id" : 756071,
    "url" : "aHR0cDovL3lvdXR1YmUuY29tL2VtYmVkL2NjeVBRb2NEaW5F",
    "episode" : 10,
    "kind" : "оригинал",
    "language" : "unknown",
    "author" : ""
  }, {
    "id" : 756072,
    "url" : "aHR0cDovL3lvdXR1YmUuY29tL2VtYmVkL3JFYTR1Sk4yT0ZZ",
    "episode" : 11,
    "kind" : "оригинал",
    "language" : "unknown",
    "author" : ""
  }, {
    "id" : 756073,
    "url" : "aHR0cDovL3lvdXR1YmUuY29tL2VtYmVkL0lxajgzaGtqYXQ0",
    "episode" : 12,
    "kind" : "оригинал",
    "language" : "unknown",
    "author" : ""
  }, {
    "id" : 756074,
    "url" : "aHR0cDovL3lvdXR1YmUuY29tL2VtYmVkL2NmRHYwRk5QVktR",
    "episode" : 13,
    "kind" : "оригинал",
    "language" : "unknown",
    "author" : ""
  } ]
}