{
  "items" : [ {
    "id" : 1660999,
    "url" : "aHR0cDovL3lvdXR1YmUuY29tL2VtYmVkL0dFWEVIV1BzUkVj",
    "episode" : 1,
    "kind" : "оригинал",
    "language" : "original",
    "author" : ""
  }, {
    "id" : 1661000,
    "url" : "aHR0cDovL3lvdXR1YmUuY29tL2VtYmVkL2wxd0RGM1EyZGJn",
    "episode" : 2,
    "kind" : "оригинал",
    "language" : "original",
    "author" : ""
  }, {
    "id" : 1661001,
    "url" : "aHR0cDovL3lvdXR1YmUuY29tL2VtYmVkL0F3OVlsWTBEejQ4",
    "episode" : 3,
    "kind" : "оригинал",
    "language" : "original",
    "author" : ""
  }, {
    "id" : 1661002,
    "url" : "aHR0cDovL3lvdXR1YmUuY29tL2VtYmVkL0JvZHdXVkFuc3Br",
    "episode" : 4,
    "kind" : "оригинал",
    "language" : "original",
    "author" : ""
  }, {
    "id" : 1661003,
    "url" : "aHR0cDovL3lvdXR1YmUuY29tL2VtYmVkL3p0TENaeWNhVEFz",
    "episode" : 5,
    "kind" : "оригинал",
    "language" : "original",
    "author" : ""
  }, {
    "id" : 1661004,
    "url" : "aHR0cDovL3lvdXR1YmUuY29tL2VtYmVkL0VLaV9rQ2RQeVJB",
    "episode" : 6,
    "kind" : "оригинал",
    "language" : "original",
    "author" : ""
  }, {
    "id" : 1661005,
    "url" : "aHR0cDovL3lvdXR1YmUuY29tL2VtYmVkLy1nYk1ST3E1NDZV",
    "episode" : 7,
    "kind" : "оригинал",
    "language" : "original",
    "author" : ""
  }, {
    "id" : 1661006,
    "url" : "aHR0cDovL3lvdXR1YmUuY29tL2VtYmVkLzd0TXlobHdvYjhv",
    "episode" : 8,
    "kind" : "оригинал",
    "language" : "original",
    "author" : ""
  }, {
    "id" : 1661007,
    "url" : "aHR0cDovL3lvdXR1YmUuY29tL2VtYmVkL2RUM3Z4dEFSVVN3",
    "episode" : 9,
    "kind" : "оригинал",
    "language" : "original",
    "author" : ""
  }, {
    "id" : 1661008,
    "url" : "aHR0cDovL3lvdXR1YmUuY29tL2VtYmVkL01GaWJmc0VKMHdF",
    "episode" : 10,
    "kind" : "оригинал",
    "language" : "original",
    "author" : ""
  }, {
    "id" : 1661009,
    "url" : "aHR0cDovL3lvdXR1YmUuY29tL2VtYmVkL05rc3BoSFRfaTAw",
    "episode" : 11,
    "kind" : "оригинал",
    "language" : "original",
    "author" : ""
  }, {
    "id" : 1661010,
    "url" : "aHR0cDovL3lvdXR1YmUuY29tL2VtYmVkL1N0WmJRQ3JpOWhB",
    "episode" : 12,
    "kind" : "оригинал",
    "language" : "original",
    "author" : ""
  }, {
    "id" : 1661011,
    "url" : "aHR0cDovL3lvdXR1YmUuY29tL2VtYmVkL09nV0ZGc1Q2N2RF",
    "episode" : 13,
    "kind" : "оригинал",
    "language" : "original",
    "author" : ""
  }, {
    "id" : 1661012,
    "url" : "aHR0cDovL3lvdXR1YmUuY29tL2VtYmVkLzBkTzM1YWZEbDNJ",
    "episode" : 14,
    "kind" : "оригинал",
    "language" : "original",
    "author" : ""
  }, {
    "id" : 1661013,
    "url" : "aHR0cDovL3lvdXR1YmUuY29tL2VtYmVkLzFjczZuZ2t1TGZF",
    "episode" : 15,
    "kind" : "оригинал",
    "language" : "original",
    "author" : ""
  }, {
    "id" : 1661014,
    "url" : "aHR0cDovL3lvdXR1YmUuY29tL2VtYmVkL21TY05OOWRCOEl3",
    "episode" : 16,
    "kind" : "оригинал",
    "language" : "original",
    "author" : ""
  }, {
    "id" : 1661015,
    "url" : "aHR0cDovL3lvdXR1YmUuY29tL2VtYmVkL2NEMTl0T0ZCeG5n",
    "episode" : 17,
    "kind" : "оригинал",
    "language" : "original",
    "author" : ""
  }, {
    "id" : 1661016,
    "url" : "aHR0cDovL3lvdXR1YmUuY29tL2VtYmVkL0hIRlNyYk1Rb3N3",
    "episode" : 18,
    "kind" : "оригинал",
    "language" : "original",
    "author" : ""
  }, {
    "id" : 1661017,
    "url" : "aHR0cDovL3lvdXR1YmUuY29tL2VtYmVkL2VheGxQVUxjeV93",
    "episode" : 19,
    "kind" : "оригинал",
    "language" : "original",
    "author" : ""
  }, {
    "id" : 1661018,
    "url" : "aHR0cDovL3lvdXR1YmUuY29tL2VtYmVkLzNTOVVJbXF3QXIw",
    "episode" : 20,
    "kind" : "оригинал",
    "language" : "original",
    "author" : ""
  }, {
    "id" : 1661019,
    "url" : "aHR0cDovL3lvdXR1YmUuY29tL2VtYmVkLzZFRFNubUlhNVEw",
    "episode" : 21,
    "kind" : "оригинал",
    "language" : "original",
    "author" : ""
  }, {
    "id" : 1661020,
    "url" : "aHR0cDovL3lvdXR1YmUuY29tL2VtYmVkL2Z1TkNtMEFrNWo0",
    "episode" : 22,
    "kind" : "оригинал",
    "language" : "original",
    "author" : ""
  }, {
    "id" : 1661021,
    "url" : "aHR0cDovL3lvdXR1YmUuY29tL2VtYmVkLzEwZTFoRWVuTXRR",
    "episode" : 23,
    "kind" : "оригинал",
    "language" : "original",
    "author" : ""
  }, {
    "id" : 1661022,
    "url" : "aHR0cDovL3lvdXR1YmUuY29tL2VtYmVkL2tONnNQZkN5dXpn",
    "episode" : 24,
    "kind" : "оригинал",
    "language" : "original",
    "author" : ""
  }, {
    "id" : 1661023,
    "url" : "aHR0cDovL3lvdXR1YmUuY29tL2VtYmVkL2VJQVNVUm8tOXlB",
    "episode" : 25,
    "kind" : "оригинал",
    "language" : "original",
    "author" : ""
  }, {
    "id" : 1661024,
    "url" : "aHR0cDovL3lvdXR1YmUuY29tL2VtYmVkL1NiRUVFLThGZkNV",
    "episode" : 26,
    "kind" : "оригинал",
    "language" : "original",
    "author" : ""
  }, {
    "id" : 1661025,
    "url" : "aHR0cDovL3lvdXR1YmUuY29tL2VtYmVkL1lDNWlIMFFHZU44",
    "episode" : 27,
    "kind" : "оригинал",
    "language" : "original",
    "author" : ""
  }, {
    "id" : 1661026,
    "url" : "aHR0cDovL3lvdXR1YmUuY29tL2VtYmVkL2V3NHRzOGIyVk9N",
    "episode" : 28,
    "kind" : "оригинал",
    "language" : "original",
    "author" : ""
  }, {
    "id" : 1661027,
    "url" : "aHR0cDovL3lvdXR1YmUuY29tL2VtYmVkL3R3OC1VbjNpYWVR",
    "episode" : 29,
    "kind" : "оригинал",
    "language" : "original",
    "author" : ""
  }, {
    "id" : 1661028,
    "url" : "aHR0cDovL3lvdXR1YmUuY29tL2VtYmVkL3YzNFJudjFWTVZ3",
    "episode" : 30,
    "kind" : "оригинал",
    "language" : "original",
    "author" : ""
  }, {
    "id" : 1661029,
    "url" : "aHR0cDovL3lvdXR1YmUuY29tL2VtYmVkL2hqQ0trNVM5STBN",
    "episode" : 31,
    "kind" : "оригинал",
    "language" : "original",
    "author" : ""
  }, {
    "id" : 1661030,
    "url" : "aHR0cDovL3lvdXR1YmUuY29tL2VtYmVkL1NBbU1USmpWNGZV",
    "episode" : 32,
    "kind" : "оригинал",
    "language" : "original",
    "author" : ""
  }, {
    "id" : 1661031,
    "url" : "aHR0cDovL3lvdXR1YmUuY29tL2VtYmVkLzF6TXV2TWhPV0k4",
    "episode" : 33,
    "kind" : "оригинал",
    "language" : "original",
    "author" : ""
  }, {
    "id" : 1661032,
    "url" : "aHR0cDovL3lvdXR1YmUuY29tL2VtYmVkL3hvTVFoRE4wZWFr",
    "episode" : 34,
    "kind" : "оригинал",
    "language" : "original",
    "author" : ""
  }, {
    "id" : 1661033,
    "url" : "aHR0cDovL3lvdXR1YmUuY29tL2VtYmVkL0Q4ekNKWTVsM29v",
    "episode" : 35,
    "kind" : "оригинал",
    "language" : "original",
    "author" : ""
  }, {
    "id" : 1661034,
    "url" : "aHR0cDovL3lvdXR1YmUuY29tL2VtYmVkL3VkY1Z5MVhaSnhB",
    "episode" : 36,
    "kind" : "оригинал",
    "language" : "original",
    "author" : ""
  }, {
    "id" : 1661035,
    "url" : "aHR0cDovL3lvdXR1YmUuY29tL2VtYmVkL1Z6c2M3dmdEUGFV",
    "episode" : 37,
    "kind" : "оригинал",
    "language" : "original",
    "author" : ""
  }, {
    "id" : 1661036,
    "url" : "aHR0cDovL3lvdXR1YmUuY29tL2VtYmVkL0ZjX2g4OGJHTXBB",
    "episode" : 38,
    "kind" : "оригинал",
    "language" : "original",
    "author" : ""
  }, {
    "id" : 1661037,
    "url" : "aHR0cDovL3lvdXR1YmUuY29tL2VtYmVkLzVKdGZoSDdzMERn",
    "episode" : 39,
    "kind" : "оригинал",
    "language" : "original",
    "author" : ""
  }, {
    "id" : 1661038,
    "url" : "aHR0cDovL3lvdXR1YmUuY29tL2VtYmVkLzhhbTRKNlRQNU9Z",
    "episode" : 40,
    "kind" : "оригинал",
    "language" : "original",
    "author" : ""
  }, {
    "id" : 1661039,
    "url" : "aHR0cDovL3lvdXR1YmUuY29tL2VtYmVkL2FUdDVva182eVQ0",
    "episode" : 41,
    "kind" : "оригинал",
    "language" : "original",
    "author" : ""
  }, {
    "id" : 1661040,
    "url" : "aHR0cDovL3lvdXR1YmUuY29tL2VtYmVkLzJ0WGVxeVEtOXV3",
    "episode" : 42,
    "kind" : "оригинал",
    "language" : "original",
    "author" : ""
  }, {
    "id" : 1661041,
    "url" : "aHR0cDovL3lvdXR1YmUuY29tL2VtYmVkL0Rqb0Z6Tl9NVXUw",
    "episode" : 43,
    "kind" : "оригинал",
    "language" : "original",
    "author" : ""
  }, {
    "id" : 1661042,
    "url" : "aHR0cDovL3lvdXR1YmUuY29tL2VtYmVkL3Y5VjMyeDgyUHZB",
    "episode" : 44,
    "kind" : "оригинал",
    "language" : "original",
    "author" : ""
  }, {
    "id" : 1661043,
    "url" : "aHR0cDovL3lvdXR1YmUuY29tL2VtYmVkLzc1d3dzTlM1UUNB",
    "episode" : 45,
    "kind" : "оригинал",
    "language" : "original",
    "author" : ""
  }, {
    "id" : 1661044,
    "url" : "aHR0cDovL3lvdXR1YmUuY29tL2VtYmVkL05zcXhLMWdPVUhZ",
    "episode" : 46,
    "kind" : "оригинал",
    "language" : "original",
    "author" : ""
  }, {
    "id" : 1661045,
    "url" : "aHR0cDovL3lvdXR1YmUuY29tL2VtYmVkL3JSV1d0VmRuNjcw",
    "episode" : 47,
    "kind" : "оригинал",
    "language" : "original",
    "author" : ""
  }, {
    "id" : 1661046,
    "url" : "aHR0cDovL3lvdXR1YmUuY29tL2VtYmVkL2FZTE85a2NtN0Zn",
    "episode" : 48,
    "kind" : "оригинал",
    "language" : "original",
    "author" : ""
  }, {
    "id" : 1661047,
    "url" : "aHR0cDovL3lvdXR1YmUuY29tL2VtYmVkL1B5YXc2LXN4NVNZ",
    "episode" : 49,
    "kind" : "оригинал",
    "language" : "original",
    "author" : ""
  }, {
    "id" : 1661048,
    "url" : "aHR0cDovL3lvdXR1YmUuY29tL2VtYmVkL2xmdUNiWExDRmNF",
    "episode" : 50,
    "kind" : "оригинал",
    "language" : "original",
    "author" : ""
  }, {
    "id" : 1661049,
    "url" : "aHR0cDovL3lvdXR1YmUuY29tL2VtYmVkL2MzdHFISEc2MjRJ",
    "episode" : 51,
    "kind" : "оригинал",
    "language" : "original",
    "author" : ""
  }, {
    "id" : 1661050,
    "url" : "aHR0cDovL3lvdXR1YmUuY29tL2VtYmVkLzJaa1hMaHphWklR",
    "episode" : 52,
    "kind" : "оригинал",
    "language" : "original",
    "author" : ""
  }, {
    "id" : 1661051,
    "url" : "aHR0cDovL3lvdXR1YmUuY29tL2VtYmVkL1hPNnZteFJYQlNZ",
    "episode" : 53,
    "kind" : "оригинал",
    "language" : "original",
    "author" : ""
  }, {
    "id" : 1661052,
    "url" : "aHR0cDovL3lvdXR1YmUuY29tL2VtYmVkL2d2aTdzNC1Oa2RZ",
    "episode" : 54,
    "kind" : "оригинал",
    "language" : "original",
    "author" : ""
  }, {
    "id" : 1661053,
    "url" : "aHR0cDovL3lvdXR1YmUuY29tL2VtYmVkL2pyaHJRRVptOFM4",
    "episode" : 55,
    "kind" : "оригинал",
    "language" : "original",
    "author" : ""
  }, {
    "id" : 1661054,
    "url" : "aHR0cDovL3lvdXR1YmUuY29tL2VtYmVkLzltQzViVjhtMU5r",
    "episode" : 56,
    "kind" : "оригинал",
    "language" : "original",
    "author" : ""
  }, {
    "id" : 1661055,
    "url" : "aHR0cDovL3lvdXR1YmUuY29tL2VtYmVkL1h6cFVYSlZ2dnFB",
    "episode" : 57,
    "kind" : "оригинал",
    "language" : "original",
    "author" : ""
  }, {
    "id" : 1661056,
    "url" : "aHR0cDovL3lvdXR1YmUuY29tL2VtYmVkL2dULWg1bHd0MG1V",
    "episode" : 58,
    "kind" : "оригинал",
    "language" : "original",
    "author" : ""
  }, {
    "id" : 1661057,
    "url" : "aHR0cDovL3lvdXR1YmUuY29tL2VtYmVkLzR3R0pqZ3A5SGdN",
    "episode" : 59,
    "kind" : "оригинал",
    "language" : "original",
    "author" : ""
  }, {
    "id" : 1661058,
    "url" : "aHR0cDovL3lvdXR1YmUuY29tL2VtYmVkLy1jM0dnYkJkSmN3",
    "episode" : 60,
    "kind" : "оригинал",
    "language" : "original",
    "author" : ""
  }, {
    "id" : 1661059,
    "url" : "aHR0cDovL3lvdXR1YmUuY29tL2VtYmVkL2dFUlJnamJNX2Rr",
    "episode" : 61,
    "kind" : "оригинал",
    "language" : "original",
    "author" : ""
  }, {
    "id" : 1661060,
    "url" : "aHR0cDovL3lvdXR1YmUuY29tL2VtYmVkL3RGeVpVTHM4aTZZ",
    "episode" : 62,
    "kind" : "оригинал",
    "language" : "original",
    "author" : ""
  }, {
    "id" : 1661061,
    "url" : "aHR0cDovL3lvdXR1YmUuY29tL2VtYmVkL0drWXJKTk5nb0pZ",
    "episode" : 63,
    "kind" : "оригинал",
    "language" : "original",
    "author" : ""
  }, {
    "id" : 1661062,
    "url" : "aHR0cDovL3lvdXR1YmUuY29tL2VtYmVkL1ZVcml3RTNFdVA4",
    "episode" : 64,
    "kind" : "оригинал",
    "language" : "original",
    "author" : ""
  }, {
    "id" : 1661063,
    "url" : "aHR0cDovL3lvdXR1YmUuY29tL2VtYmVkL2wwd0xxTF9RWDhJ",
    "episode" : 65,
    "kind" : "оригинал",
    "language" : "original",
    "author" : ""
  }, {
    "id" : 1661064,
    "url" : "aHR0cDovL3lvdXR1YmUuY29tL2VtYmVkL3owLUdibXVwUVdN",
    "episode" : 66,
    "kind" : "оригинал",
    "language" : "original",
    "author" : ""
  }, {
    "id" : 1661065,
    "url" : "aHR0cDovL3lvdXR1YmUuY29tL2VtYmVkL2p6VDJCTk0zcjNN",
    "episode" : 67,
    "kind" : "оригинал",
    "language" : "original",
    "author" : ""
  }, {
    "id" : 1661066,
    "url" : "aHR0cDovL3lvdXR1YmUuY29tL2VtYmVkLzZhNC13OThFN0NV",
    "episode" : 68,
    "kind" : "оригинал",
    "language" : "original",
    "author" : ""
  }, {
    "id" : 1661067,
    "url" : "aHR0cDovL3lvdXR1YmUuY29tL2VtYmVkL3I1d0FfejJGZndr",
    "episode" : 69,
    "kind" : "оригинал",
    "language" : "original",
    "author" : ""
  }, {
    "id" : 1661068,
    "url" : "aHR0cDovL3lvdXR1YmUuY29tL2VtYmVkL2xhei1pWmZURlZR",
    "episode" : 70,
    "kind" : "оригинал",
    "language" : "original",
    "author" : ""
  }, {
    "id" : 1661069,
    "url" : "aHR0cDovL3lvdXR1YmUuY29tL2VtYmVkL2RxNkxIZzRaNFlj",
    "episode" : 71,
    "kind" : "оригинал",
    "language" : "original",
    "author" : ""
  }, {
    "id" : 1661070,
    "url" : "aHR0cDovL3lvdXR1YmUuY29tL2VtYmVkL19jRG9CcGMxTWVN",
    "episode" : 72,
    "kind" : "оригинал",
    "language" : "original",
    "author" : ""
  }, {
    "id" : 1661071,
    "url" : "aHR0cDovL3lvdXR1YmUuY29tL2VtYmVkL1FCcmNpOWdNdmNR",
    "episode" : 73,
    "kind" : "оригинал",
    "language" : "original",
    "author" : ""
  }, {
    "id" : 1661072,
    "url" : "aHR0cDovL3lvdXR1YmUuY29tL2VtYmVkL1hzTmp5ajR4UVFF",
    "episode" : 74,
    "kind" : "оригинал",
    "language" : "original",
    "author" : ""
  }, {
    "id" : 1661073,
    "url" : "aHR0cDovL3lvdXR1YmUuY29tL2VtYmVkL19EbngzR28wcUlR",
    "episode" : 75,
    "kind" : "оригинал",
    "language" : "original",
    "author" : ""
  }, {
    "id" : 1661074,
    "url" : "aHR0cDovL3lvdXR1YmUuY29tL2VtYmVkL2RfTGlvdmJBVUxV",
    "episode" : 76,
    "kind" : "оригинал",
    "language" : "original",
    "author" : ""
  }, {
    "id" : 1661075,
    "url" : "aHR0cDovL3lvdXR1YmUuY29tL2VtYmVkL3EyaU1kZG5Db1ZJ",
    "episode" : 77,
    "kind" : "оригинал",
    "language" : "original",
    "author" : ""
  }, {
    "id" : 1661076,
    "url" : "aHR0cDovL3lvdXR1YmUuY29tL2VtYmVkL2JtNlo4eWF2Sm5j",
    "episode" : 78,
    "kind" : "оригинал",
    "language" : "original",
    "author" : ""
  }, {
    "id" : 1661077,
    "url" : "aHR0cDovL3lvdXR1YmUuY29tL2VtYmVkL3l0VElITEw3dDc4",
    "episode" : 79,
    "kind" : "оригинал",
    "language" : "original",
    "author" : ""
  }, {
    "id" : 1661078,
    "url" : "aHR0cDovL3lvdXR1YmUuY29tL2VtYmVkL1k5UUJYS0txOHMw",
    "episode" : 80,
    "kind" : "оригинал",
    "language" : "original",
    "author" : ""
  }, {
    "id" : 1661080,
    "url" : "aHR0cDovL3lvdXR1YmUuY29tL2VtYmVkL3E5VnMtdHhXV3Nz",
    "episode" : 81,
    "kind" : "оригинал",
    "language" : "original",
    "author" : ""
  }, {
    "id" : 1661082,
    "url" : "aHR0cDovL3lvdXR1YmUuY29tL2VtYmVkL2dCTDhTWTFZaEFn",
    "episode" : 82,
    "kind" : "оригинал",
    "language" : "original",
    "author" : ""
  }, {
    "id" : 1661083,
    "url" : "aHR0cDovL3lvdXR1YmUuY29tL2VtYmVkL0FyOE91QS1JVlE4",
    "episode" : 83,
    "kind" : "оригинал",
    "language" : "original",
    "author" : ""
  }, {
    "id" : 1661084,
    "url" : "aHR0cDovL3lvdXR1YmUuY29tL2VtYmVkL0RvWnkyZi12S1FJ",
    "episode" : 84,
    "kind" : "оригинал",
    "language" : "original",
    "author" : ""
  }, {
    "id" : 1661085,
    "url" : "aHR0cDovL3lvdXR1YmUuY29tL2VtYmVkLzZ6ZkV5YThvbFV3",
    "episode" : 85,
    "kind" : "оригинал",
    "language" : "original",
    "author" : ""
  }, {
    "id" : 1661086,
    "url" : "aHR0cDovL3lvdXR1YmUuY29tL2VtYmVkL05ZdWJEeW96RDk4",
    "episode" : 86,
    "kind" : "оригинал",
    "language" : "original",
    "author" : ""
  }, {
    "id" : 1661087,
    "url" : "aHR0cDovL3lvdXR1YmUuY29tL2VtYmVkLzlWNXp5alBXTzI4",
    "episode" : 87,
    "kind" : "оригинал",
    "language" : "original",
    "author" : ""
  }, {
    "id" : 1661088,
    "url" : "aHR0cDovL3lvdXR1YmUuY29tL2VtYmVkL18yUWI2YmlfX2Q4",
    "episode" : 88,
    "kind" : "оригинал",
    "language" : "original",
    "author" : ""
  }, {
    "id" : 1661089,
    "url" : "aHR0cDovL3lvdXR1YmUuY29tL2VtYmVkL1k1MHBZSDNwWjZF",
    "episode" : 89,
    "kind" : "оригинал",
    "language" : "original",
    "author" : ""
  }, {
    "id" : 1661090,
    "url" : "aHR0cDovL3lvdXR1YmUuY29tL2VtYmVkLzE0Q1ZEMWV4VEhr",
    "episode" : 90,
    "kind" : "оригинал",
    "language" : "original",
    "author" : ""
  }, {
    "id" : 1661091,
    "url" : "aHR0cDovL3lvdXR1YmUuY29tL2VtYmVkL3VFWHM3Z2FfTkcw",
    "episode" : 91,
    "kind" : "оригинал",
    "language" : "original",
    "author" : ""
  }, {
    "id" : 1661092,
    "url" : "aHR0cDovL3lvdXR1YmUuY29tL2VtYmVkL3ozZXRyaXE5MUhN",
    "episode" : 92,
    "kind" : "оригинал",
    "language" : "original",
    "author" : ""
  }, {
    "id" : 1661093,
    "url" : "aHR0cDovL3lvdXR1YmUuY29tL2VtYmVkL3BoWmo1WEMySWM4",
    "episode" : 93,
    "kind" : "оригинал",
    "language" : "original",
    "author" : ""
  }, {
    "id" : 1661094,
    "url" : "aHR0cDovL3lvdXR1YmUuY29tL2VtYmVkL2xhazlFMnQ5Z2VZ",
    "episode" : 94,
    "kind" : "оригинал",
    "language" : "original",
    "author" : ""
  }, {
    "id" : 1661095,
    "url" : "aHR0cDovL3lvdXR1YmUuY29tL2VtYmVkL055UTR0QmUzV2tR",
    "episode" : 95,
    "kind" : "оригинал",
    "language" : "original",
    "author" : ""
  }, {
    "id" : 1661096,
    "url" : "aHR0cDovL3lvdXR1YmUuY29tL2VtYmVkL3hVelNEV1lDZzl3",
    "episode" : 96,
    "kind" : "оригинал",
    "language" : "original",
    "author" : ""
  }, {
    "id" : 1661097,
    "url" : "aHR0cDovL3lvdXR1YmUuY29tL2VtYmVkL25hbzdZenJiQ0Fz",
    "episode" : 97,
    "kind" : "оригинал",
    "language" : "original",
    "author" : ""
  }, {
    "id" : 1661098,
    "url" : "aHR0cDovL3lvdXR1YmUuY29tL2VtYmVkLzJVcVAyWGlCRHFR",
    "episode" : 98,
    "kind" : "оригинал",
    "language" : "original",
    "author" : ""
  }, {
    "id" : 1661099,
    "url" : "aHR0cDovL3lvdXR1YmUuY29tL2VtYmVkLzd0UUNQcHNNcS1v",
    "episode" : 99,
    "kind" : "оригинал",
    "language" : "original",
    "author" : ""
  }, {
    "id" : 1661100,
    "url" : "aHR0cDovL3lvdXR1YmUuY29tL2VtYmVkL2pjWXZpeWtfSkQ4",
    "episode" : 100,
    "kind" : "оригинал",
    "language" : "original",
    "author" : ""
  }, {
    "id" : 1661101,
    "url" : "aHR0cDovL3lvdXR1YmUuY29tL2VtYmVkL1dNMmRpVzY4cDVZ",
    "episode" : 101,
    "kind" : "оригинал",
    "language" : "original",
    "author" : ""
  }, {
    "id" : 1661102,
    "url" : "aHR0cDovL3lvdXR1YmUuY29tL2VtYmVkL21fQ0hoQW1QVG5N",
    "episode" : 102,
    "kind" : "оригинал",
    "language" : "original",
    "author" : ""
  }, {
    "id" : 1661103,
    "url" : "aHR0cDovL3lvdXR1YmUuY29tL2VtYmVkL3Fid2N2alRlVUw4",
    "episode" : 103,
    "kind" : "оригинал",
    "language" : "original",
    "author" : ""
  }, {
    "id" : 1661104,
    "url" : "aHR0cDovL3lvdXR1YmUuY29tL2VtYmVkL05nYXJFOWpXcHVV",
    "episode" : 104,
    "kind" : "оригинал",
    "language" : "original",
    "author" : ""
  } ]
}